[
 {
  "source": "「嗯—… %MASTER_CALL()%の手つき、結構優しんだな…」",
  "target": "「嗯—… %MASTER_CALL()%的手法、还挺温柔的呢…」"
 },
 {
  "source": "「啊♥ 啊♥ 声が…っ 抑えられな……ん啊♥」",
  "target": "「啊♥ 啊♥ 声音…っ 忍不住了……嗯啊♥」"
 },
 {
  "source": "「呜呜…♥ あんまぐいぐい動かすなぁ…♥」",
  "target": "「呜呜…♥ 别那么用力地抽动啊ぁ…♥」"
 },
 {
  "source": "「あ呜呜♥ 里面をくちゅくちゅされてる…♥」",
  "target": "「啊呜呜♥ 里面被咕啾咕啾地搅动着…♥」"
 },
 {
  "source": "「はぅ…っ！ ゆび、いれられてる…っ」",
  "target": "「哈呜…っ！ 手指、被放进来了…っ」"
 },
 {
  "source": "「ひぅ……う、動かすなよぉ…」",
  "target": "「咿呜……不、别动啊ぉ…」"
 },
 {
  "source": "「啊呜…！♥ ゆ、ゆびぃっ♥ ゆびが%ANAL_CALL()%にぃ♥♥ んおぉっ♥♥」",
  "target": "「啊呜…！♥ 手、手指ぃっ♥ 手指进%ANAL_CALL()%了ぃ♥♥ 嗯哦哦っ♥♥」"
 },
 {
  "source": "「咿咕！？♥ そ、そんな地方に指を…♥」",
  "target": "「咿咕！？♥ 那、那种地方手指…♥」"
 },
 {
  "source": "「ふ咕呜っ！？ ど、どこに指を挿れてんだ…っ」",
  "target": "「呼咕呜っ！？ 你、你往哪儿插手指呢…っ」"
 },
 {
  "source": "「んおぉっ♥♥ %ANAL_CALL()%呃♥ 指ズボズボしてりゅっ♥♥ 哦♥ 哦ー~♥♥♥」",
  "target": "「嗯哦ぉっ♥♥ %ANAL_CALL()%呃♥ 手指噗咻噗咻地进进出出っ♥♥ 哦♥ 哦ー~♥♥♥」"
 },
 {
  "source": "「はおぉ♥♥ %ANAL_CALL()%で有感觉なんて♥♥ 变态で对不起ぃ♥♥♥」",
  "target": "「哈哦ぉ♥♥ 居然因%ANAL_CALL()%有感觉♥♥ 变态真是对不起ぃ♥♥♥」"
 },
 {
  "source": "「ん咿♥♥ し、死ぬほど恥ずかしいのにっ♥♥ 感じちまってるぅっ♥♥」",
  "target": "「嗯咿♥♥ 虽、虽然羞耻得要死っ♥♥ 但还是有感觉了ぅっ♥♥」"
 },
 {
  "source": "「は、は咿♥♥ 里面で指動かすのはダメだってぇ♥♥」",
  "target": "「哈、哈咿♥♥ 在里面动手指是不行的啦ぇ♥♥」"
 },
 {
  "source": "「ほーっ♥♥ ほーっ♥♥ %SELF_CALL()%はカンチョーで高潮する变态に調教されまひたぁ♥♥」",
  "target": "「吼—っ♥♥ 吼—っ♥♥ %SELF_CALL()%被调教成灌肠就高潮的变态了ぁ♥♥」"
 },
 {
  "source": "「%SWEET_MASTER_CALL()%♥♥ 指で念入りにほぐしてるってことは…♥♥\n　%PENIS_CALL()%でいっぱい責めてもらえるの、期待していいよな…？♥♥」",
  "target": "「%SWEET_MASTER_CALL()%♥♥ 用手指仔仔细细地放松的话…♥♥\n　就可以期待被%PENIS_CALL()%好好疼爱一番了吧…？♥♥」"
 },
 {
  "source": "「は、はれっ？♥♥ %MASTER_CALL()%、手を動かしてない…？♥♥\n　%SELF_CALL()%、無意識に腰振ってた…？♥♥」",
  "target": "「哈、哈咧？♥♥ %MASTER_CALL()%、手没有在动…？♥♥\n　%SELF_CALL()%、无意识地自己扭腰了…？♥♥」"
 },
 {
  "source": "「んやぁ…%ANAL_CALL()%をぐちょぐちょ掻き回されたらぁ…♥♥」",
  "target": "「嗯啊ぁ…%ANAL_CALL()%被咕啾咕啾地搅动的话ぁ…♥♥」"
 },
 {
  "source": "「ん啊呜♥♥ ぬ、濡れてないのに強引に…っ♥ 哦♥ 啊呜♥」",
  "target": "「嗯啊呜♥♥ 又、又没湿还这么强行来…っ♥ 哦♥ 啊呜♥」"
 },
 {
  "source": "「んぎぃっ！？♥ %MASTER_CALL()%っ…い、痛い…っ」",
  "target": "「嗯咿ぃっ！？♥ %MASTER_CALL()%っ…好、好痛…っ」"
 },
 {
  "source": "「そ、そんなところっ…どうかしてる…っ！」",
  "target": "「那、那种地方っ…你有病吧…っ！」"
 },
 {
  "source": "「%SELF_CALL()%の尻…♥ 触り心地はどうだ？♥♥」",
  "target": "「%SELF_CALL()%的屁股…♥ 摸起来怎么样啊？♥♥」"
 },
 {
  "source": "「嘻嘻 %MASTER_CALL()%、すげえ好色手つきだな♥♥」",
  "target": "「嘻嘻 %MASTER_CALL()%、手法真够好色的呢♥♥」"
 },
 {
  "source": "「啊♥ …焦らすような撫で方で意地悪ばっか…♥♥」",
  "target": "「啊♥ …用挑逗一样的摸法净使坏…♥♥」"
 },
 {
  "source": "「なぁ…%SELF_CALL()%って筋肉質でどうも女らしくない身体だよなぁ…\n「え、えぇ…♥ 褒めてくれるのは%MASTER_CALL()%只是だよ…♥♥」",
  "target": "「呐…%SELF_CALL()%这肌肉发达一点都不女人的身体啊…\n「诶、诶ぇ…♥ 会夸我的只有%MASTER_CALL()%了啦…♥♥」"
 },
 {
  "source": "「なぁ…%SELF_CALL()%って脂肪が多い分、尻も柔らかいかな…とか……呜呜…♥」",
  "target": "「呐…%SELF_CALL()%脂肪多、屁股会不会也软一点呢…之类的……呜呜…♥」"
 },
 {
  "source": "「%MASTER_CALL()%…♥ %CSTR:体型%で肉感たっぷりの尻♥ 撫で心地はどうだ♥」",
  "target": "「%MASTER_CALL()%…♥ %CSTR:体型%的肉感屁股♥ 摸起来怎么样啊♥」"
 },
 {
  "source": "「嗯……♥ いきなり撫でるのはやめてくれ…」",
  "target": "「嗯……♥ 突然摸过来别这样啊…」"
 },
 {
  "source": "「……好色手つきで触んじゃねえ…」",
  "target": "「……别用那么好色的手法碰啊…」"
 },
 {
  "source": "「ん哈啊♥♥ 焦らされてるみたいで興奮してきた♥♥」",
  "target": "「嗯哈啊♥♥ 感觉像在被挑逗一样兴奋起来了♥♥」"
 },
 {
  "source": "「ふぁ…♥ 優しくされるの…好き也许…♥♥」",
  "target": "「呼啊…♥ 被温柔对待…也许喜欢…♥♥」"
 },
 {
  "source": "「は呜呜♥ なんか品定めされてるみたいだ…♥♥」",
  "target": "「哈呜呜♥ 总感觉像是在被估价一样…♥♥」"
 },
 {
  "source": "「哈啊…♥ いつ鷲掴みにされるかって…ドキドキする…♥♥」",
  "target": "「哈啊…♥ 不知道什么时候会被一把抓住…心跳得好快…♥♥」"
 },
 {
  "source": "「啊♥ 小奶子まさぐられてドキドキする♥♥」",
  "target": "「啊♥ 小奶子被摸来摸去心跳得好快♥♥」"
 },
 {
  "source": "「や、優しくしろよ…♥」",
  "target": "「要、要温柔点啊…♥」"
 },
 {
  "source": "「さ、触んじゃねえ…っ」",
  "target": "「别、别碰啊…っ」"
 },
 {
  "source": "「ふっ…♥ べ、べつに良くなんてねえ…っ♥」",
  "target": "「呼っ…♥ 才、才没有舒服呢…っ♥」"
 },
 {
  "source": "「くひひ咿♥ やめ、ふ咿♥ 应该かし…からっ♥ 咿ぃひひ咿♥」",
  "target": "「咕嘻嘻咿っ♥ 住手、呼咿っ♥ 好羞耻…っ♥ 咿ぃ嘻嘻咿っ♥」"
 },
 {
  "source": "「は、は咿♥ く、くるし…♥ やめっ…咿っ♥」",
  "target": "「哈、哈咿♥ 好、好难受…♥ 停下っ…咿っ♥」"
 },
 {
  "source": "「咕呜ぅ…腹に触られると…里面で触手がぁ…っ」",
  "target": "「咕呜呜…肚子被触碰的话…里面的触手就ぁ…っ」"
 },
 {
  "source": "\\d%CALLNAME%のお腹は%CALLNAME:0%の子を宿して膨らんでいる…\\d\n\n「呼呼♥♥ 腹の赤んぼによしよし、ってしてやってくれよ♥♥」",
  "target": "\\d%CALLNAME%的肚子里怀着%CALLNAME:0%的孩子鼓起来了…\\d\n\n「呼呼♥♥ 给肚子里的宝宝摸摸头、说乖乖哦♥♥」"
 },
 {
  "source": "「哈咿…♥♥ %MASTER_CALL()%の精液で腹がこんなに膨らんで…♥♥」",
  "target": "「哈咿…♥♥ 肚子被%MASTER_CALL()%的精液撑得这么鼓了…♥♥」"
 },
 {
  "source": "「呼呼♥ くすぐったいって…♥♥」",
  "target": "「呼呼♥ 好痒啦…♥♥」"
 },
 {
  "source": "「へへ♥ そのうち外から子宮を刺激して、能去ようになる也许…♥♥」",
  "target": "「嘿嘿♥ 也许以后从外面刺激子宫、就能去了呢…♥♥」"
 },
 {
  "source": "「なぁ、%MASTER_CALL()%…腹筋を撫でるのが好きなのか…？」",
  "target": "「呐、%MASTER_CALL()%…你喜欢摸腹肌吗…？」"
 },
 {
  "source": "「あ、あぅ…脂肪がついた腹撫でられんのは恥ずかしい也许…」",
  "target": "「啊、啊呜…长了脂肪的肚子被摸也许很羞耻…」"
 },
 {
  "source": "「は、恥ずかしいから…あんま腹の肉で遊ばないでくれって……」",
  "target": "「很、很羞耻的…别老拿肚子上的肉玩啦……」"
 },
 {
  "source": "「んぁっ♥ %PENIS_CALL()%の動きに合わせて腹が盛り上がるの、分かるか？♥♥」",
  "target": "「嗯啊っ♥ 肚子随着%PENIS_CALL()%的动作鼓起来、看到了吗？♥♥」"
 },
 {
  "source": "\\d%CALLNAME%のお腹は%CALLNAME:0%の子を宿して膨らんでいる…\\d\n\n「哈啊……妊娠までさせられるとはな……」",
  "target": "\\d%CALLNAME%的肚子里怀着%CALLNAME:0%的孩子鼓起来了…\\d\n\n「哈啊……连怀孕都被你搞出来了啊……」"
 },
 {
  "source": "「嗯…くすぐたいって…」",
  "target": "「嗯…好痒啦…」"
 },
 {
  "source": "「……腹がどうかしたか…？」",
  "target": "「……肚子怎么了…？」"
 },
 {
  "source": "\\d%CALLNAME%のお腹は%CALLNAME:0%の子を宿して膨らんでいる…\\d\n\n「う咕呜…こんな場所で孕まされて……ゆるさねえ…」",
  "target": "\\d%CALLNAME%的肚子里怀着%CALLNAME:0%的孩子鼓起来了…\\d\n\n「呜咕呜…被在这种地方搞怀孕……不可饶恕…」"
 },
 {
  "source": "「ぅぐ…出されすぎて……くる…しぃ……」",
  "target": "「呜咕…被射太多了……好、难受……」"
 },
 {
  "source": "「は咿♥ 淫紋に触られると…っ♥ 啊♥ 啊♥」",
  "target": "「哈咿♥ 淫纹被碰到的话…っ♥ 啊♥ 啊♥」"
 },
 {
  "source": "「………触んなって…」",
  "target": "「……说了别碰…」"
 },
 {
  "source": "「は咿♥…ん咿っ♥…%SWEET_MASTER_CALL()%っ♥♥ 谢谢ございましゅぅっ♥♥」",
  "target": "「哈咿っ♥…嗯咿ぃっ♥…%SWEET_MASTER_CALL()%っ♥♥ 谢谢你咻ぅっ♥♥」"
 },
 {
  "source": "「はぅっ♥……啊啊、不行ぇ…腰が無意識にふりふり動いて、おかわり欲しがってるぅ♥♥」",
  "target": "「哈呜っ♥……啊啊、不行ぇ…腰不自觉地扭来扭去、在讨要更多ぅ♥♥」"
 },
 {
  "source": "「あ咿♥…ん啊♥…更加ぉ…更加強くしてくれぇ…♥♥」",
  "target": "「啊咿♥…嗯啊♥…更加ぉ…更用力地干我ぇ…♥♥」"
 },
 {
  "source": "「は呜呜っ♥♥……%SWEET_MASTER_CALL()%♥♥ たっぷりお惩罚をください♥♥」",
  "target": "「哈呜呜っ♥♥……%SWEET_MASTER_CALL()%♥♥ 请好好惩罚我吧♥♥」"
 },
 {
  "source": "「んい゛ぃっ♥♥ 尻ぶたれながら%VAGINA_CALL()%を犯されるの、さいっこぉ…っ♥♥」",
  "target": "「嗯い゛ぃっ♥♥ 一边被打屁股一边被干%VAGINA_CALL()%、最棒了ぉ…っ♥♥」"
 },
 {
  "source": "「は咿♥ 叩かれる度に%VAGINA_CALL()%がキュッ♥キュッ♥って%PENIS_CALL()%締めつけてるっ♥♥」",
  "target": "「哈咿♥ 每次被拍打%VAGINA_CALL()%都会紧缩♥啾♥啾地夹紧%PENIS_CALL()%っ♥♥」"
 },
 {
  "source": "「嗯哦~♥♥ 尻をビンタされながら%ANAL_CALL()%ほじられてるっ♥♥」",
  "target": "「嗯哦~♥♥ 一边被打屁股一边被抠%ANAL_CALL()%っ♥♥」"
 },
 {
  "source": "「ふぎぃ♥♥ 尻穴セックスとかスパンキングみたいな变态プレイでぇ…♥♥\n　あんあん喘いで即高潮する身体になっちまったぁ♥♥ んおおぉっ♥♥」",
  "target": "「呼咿ぃ♥♥ 后穴性交啦拍打啦之类的变态玩法ぇ…♥♥\n　啊啊娇喘着变成一碰就高潮的身体了ぁ♥♥ 嗯哦哦ぉっ♥♥」"
 },
 {
  "source": "「ん咿っ♥♥ お惩罚アナルセックスしてくれるドSに支配してもらえて幸せぇっ♥♥」",
  "target": "「嗯咿っ♥♥ 被用惩罚后穴性交的抖S支配好幸福ぇっ♥♥」"
 },
 {
  "source": "「啊咿♥♥ 拘束されながら%ANAL_CALL()%犯されて悦んでる变态マゾにぃ♥♥\n　尻ビンタのご褒美谢谢ございましゅぅ♥♥♥」",
  "target": "「啊咿♥♥ 被拘束着干%ANAL_CALL()%还一脸享受的变态抖Mぃ♥♥\n　打屁股的奖励谢谢你咻ぅ♥♥♥」"
 },
 {
  "source": "「お、おぉ…♥♥ 処女のクセに、%ANAL_CALL()%ハメられながらケツ叩きで悦ぶ变态にされちまった…♥♥」",
  "target": "「哦、哦哦…♥♥ 明明是处女、却被干%ANAL_CALL()%加打屁股还能发骚的变态了…♥♥」"
 },
 {
  "source": "「ん咿っ♥……饱满に実ったでっかい尻♥ 今が食べごろだぞぉ♥♥」",
  "target": "「嗯咿っ♥……饱满成熟的大屁股♥ 现在正是吃的时候哦ぉ♥♥」"
 },
 {
  "source": "「ん哈啊♥♥ ……拘束スパンキング……ヘンタイちっくで興奮する♥♥」",
  "target": "「嗯哈啊♥♥ ……拘束打屁股……真是变态好兴奋♥♥」"
 },
 {
  "source": "「ひぅっ♥…ぁ啊♥……目隠しされると、いつ来るかって一層ドキドキする♥♥」",
  "target": "「咿呜っ♥…啊啊♥……被蒙上眼的话、不知道什么时候会来就更心跳加速了♥♥」"
 },
 {
  "source": "「咿咕！…ん嗯…%MASTER_CALL()%っ…あぅっ…！」",
  "target": "「咿咕っ！…嗯嗯…%MASTER_CALL()%っ…啊呜っ…！」"
 },
 {
  "source": "「あ咿♥…は咿♥……%SELF_CALL()%、痛いのに有感觉る…っ♥」",
  "target": "「啊咿♥…哈咿♥……%SELF_CALL()%、明明很痛却有感觉…っ♥」"
 },
 {
  "source": "「はぅっ♥…啊啊っ♥……お尻、ジンジンする…♥」",
  "target": "「哈呜っ♥…啊啊っ♥……屁股、一阵阵发麻…♥」"
 },
 {
  "source": "「あ咿♥…んいぃっ♥……は呜呜♥♥」",
  "target": "「啊咿♥…嗯咿ぃっ♥……哈呜呜♥♥」"
 },
 {
  "source": "「あぅっ♥……こ、こんなモンかよ…っ♥」",
  "target": "「啊呜っ♥……就、就这样吗…っ♥」"
 },
 {
  "source": "「咕呜っ♥ 尻を叩かれて、余計に有感觉る気がするぅ…っ♥」",
  "target": "「咕呜っ♥ 被打了屁股、反而更有感觉了ぅ…っ♥」"
 },
 {
  "source": "「がぁっ♥ バシバシ叩きながら尻を犯しやがってぇ♥♥」",
  "target": "「嘎ぁっ♥ 一边啪啪地打一边干屁股、真有你的ぇ♥♥」"
 },
 {
  "source": "「%SWEET_MASTER_CALL()%♥♥ すけべな勃起乳头を更加強く吸ってくれぇ♥♥」",
  "target": "「%SWEET_MASTER_CALL()%♥♥ 更用力地吸我这好色的勃起乳头吧ぇ♥♥」"
 },
 {
  "source": "「呵呵…♥ 不要らしく育ったこの胸♥ 喜んでもらえたみたいで嬉しいよ♥♥♥」",
  "target": "「呵呵…♥ 这下流地长起来的胸部♥ 能让你高兴我好开心啊♥♥♥」"
 },
 {
  "source": "「%SWEET_MASTER_CALL()%♥♥ そんなに吸われたら我慢できなくなるぅ…♥♥」",
  "target": "「%SWEET_MASTER_CALL()%♥♥ 被那么吸的话我会忍不住的ぅ…♥♥」"
 },
 {
  "source": "「どうよ…甘えがいのあるでっかい奶子…♥♥ 気に入ってくれたか？♥♥」",
  "target": "「怎么样…值得撒娇的大奶子…♥♥ 喜欢上了吗？♥♥」"
 },
 {
  "source": "「むっちり奶子で%MASTER_CALL()%を抱っこしてやるよ…♥\n　なんも考えずに…ちゅぱ♥ちゅぱ♥甘えていいからな…♥♥」",
  "target": "「用肉乎乎的奶子抱着%MASTER_CALL()%…♥\n　什么也不用想…啾啪♥啾啪♥尽情撒娇就好…♥♥」"
 },
 {
  "source": "「ん嗯…♥ 小さな胸でも%MASTER_CALL()%に愉しんでもらえて嬉しいよ…♥♥」",
  "target": "「嗯嗯…♥ 小小的胸部也能让%MASTER_CALL()%享受、我好开心啊…♥♥」"
 },
 {
  "source": "「よしよし♥♥ 更加赤んぼみたいに甘えていいんだぜ…♥♥」",
  "target": "「乖哦乖哦♥♥ 可以更像个宝宝一样撒娇哦…♥♥」"
 },
 {
  "source": "「啊♥ そんなに必死で吸いついてんじゃ…♥」",
  "target": "「啊♥ 别那么拼命地吸上来啊…♥」"
 },
 {
  "source": "「赤んぼでもないヤツに吸い付かれるなんてよ…」",
  "target": "「又不是小婴儿还被吸住不放啊…」"
 },
 {
  "source": "「啊啊…♥ 果然直で飲んでもらえるのが家畜として一番うれしいな♥♥♥」",
  "target": "「啊啊…♥ 果然直接喝才是作为家畜最开心的事呢♥♥♥」"
 },
 {
  "source": "「%MASTER_CALL()%専用の乳汁サーバー♥♥ いっぱい使ってくだひゃい♥♥」",
  "target": "「%MASTER_CALL()%专用乳汁服务器♥♥ 请多多使用咿♥♥」"
 },
 {
  "source": "「%SELF_CALL()%、母牛にしてもらえて幸せだ…♥♥ いっぱい飲んでほしい♥♥」",
  "target": "「%SELF_CALL()%、能被当成乳牛好幸福啊…♥♥ 想让你多喝点♥♥」"
 },
 {
  "source": "「%SWEET_MASTER_CALL()%♥ 奶子切なくて…吸い尽くしてほしいんだ♥♥」",
  "target": "「%SWEET_MASTER_CALL()%♥ 奶子好难受…想让你吸干净♥♥」"
 },
 {
  "source": "「はー♥ はー♥ お代わり自由所以いっぱい飲んでいいぞ♥♥」",
  "target": "「哈ー♥ 哈ー♥ 可以随便续杯所以多喝点哦♥♥」"
 },
 {
  "source": "「でっかく育った乳牛奶子♥ %MASTER_CALL()%に飲んでもらえて嬉しいよ♥♥」",
  "target": "「长得大大的乳牛奶子♥ 能被%MASTER_CALL()%喝好开心啊♥♥」"
 },
 {
  "source": "「小ぶりでも一人前の母牛奶子所以、いっぱい飲んでくれよな♥♥」",
  "target": "「虽然小巧但也是合格的母牛奶子、多喝点哦♥♥」"
 },
 {
  "source": "「嗯……♥ 胸が小さくても、美味しい母乳になるよう頑張るからな…♥♥」",
  "target": "「嗯……♥ 胸虽然小、但我会努力产出好喝的母乳的…♥♥」"
 },
 {
  "source": "「%SWEET_MASTER_CALL()%♥♥ 生搾り小奶子乳汁♥♥ いっぱい飲むんだぞ…♥♥」",
  "target": "「%SWEET_MASTER_CALL()%♥♥ 现挤的小奶子乳汁♥♥ 要多喝点哦…♥♥」"
 },
 {
  "source": "「啊啊嗯♥♥ 拘束されちまって、まさに乳汁サーバー状態じゃんかぁ♥♥♥」",
  "target": "「啊啊嗯♥♥ 被拘束起来、这不就是乳汁服务器状态嘛ぁ♥♥♥」"
 },
 {
  "source": "「嘻嘻 愛情たっぷりの乳汁…美味いに決まってるよな♥♥」",
  "target": "「嘻嘻 充满爱意的乳汁…当然好喝啦♥♥」"
 },
 {
  "source": "「啊啊…♥♥ 惚れた相手に授乳してやるのがこんなに幸せとはなぁ…♥♥」",
  "target": "「啊啊…♥♥ 给喜欢的人喂奶居然这么幸福啊ぁ…♥♥」"
 },
 {
  "source": "「%MASTER_CALL()%♥♥ 満足するまで味わってくれよな♥♥」",
  "target": "「%MASTER_CALL()%♥♥ 好好品尝直到满意为止哦♥♥」"
 },
 {
  "source": "「啊啊…♥ そんなに美味そうに飲んでくれるなんて…♥♥」",
  "target": "「啊啊…♥ 喝得那么香的样子…♥♥」"
 },
 {
  "source": "「はふぅ♥♥ %MASTER_CALL()%に直接飲んでもらえると、嬉しくて胸が一杯になるんだよ♥♥」",
  "target": "「哈呼ぅ♥♥ 能被%MASTER_CALL()%直接喝、心里就满满的都是开心呢♥♥」"
 },
 {
  "source": "「啊啊嗯♥♥ そんなにがっつかなくても、いっぱい出すからぁ♥♥」",
  "target": "「啊啊嗯♥♥ 不用那么着急、我会出很多的啦ぁ♥♥」"
 },
 {
  "source": "「この通り饱满に実ってるからさ♥♥ たんと飲んでくれよな♥♥」",
  "target": "「你看长得这么饱满♥♥ 多喝点吧♥♥」"
 },
 {
  "source": "「あん…♥♥ %SELF_CALL()%のロリ乳汁♥♥ ホント美味そうに飲むよなぁ…♥♥」",
  "target": "「嗯…♥♥ %SELF_CALL()%的萝莉乳汁♥♥ 喝得真香啊ぁ…♥♥」"
 },
 {
  "source": "「子供体温のホット乳汁で身体がぽかぽか暖まってきたろ♥♥」",
  "target": "「用孩子体温的热乳汁身体都暖和起来了吧♥♥」"
 },
 {
  "source": "「～～♥ す、吸いすぎだって…っ♥」",
  "target": "「～～♥ 都、都说吸太多了…っ♥」"
 },
 {
  "source": "「喂，♥ そんなにがっつくなって…♥」",
  "target": "「喂，♥ 别那么急吼吼的…♥」"
 },
 {
  "source": "「は、離せよっ…飲んでんじゃね诶…！」",
  "target": "「放、放开我っ…别喝啊诶…！」"
 },
 {
  "source": "「%SWEET_MASTER_CALL()%♥♥ 指で念入りにほぐしてるってことは…♥♥\\n　%PENIS_CALL()%でいっぱい責めてもらえるの、期待していいよな…？♥♥」",
  "target": "「%SWEET_MASTER_CALL()%♥♥ 用手指这么仔细地给我放松…♥♥\\n　也就是说能让%PENIS_CALL()%好好干我一顿，可以期待的…对吧…？♥♥」"
 },
 {
  "source": "「は、はれっ？♥♥ %MASTER_CALL()%、手を動かしてない…？♥♥\\n　%SELF_CALL()%、無意識に腰振ってた…？♥♥」",
  "target": "「哈、哈啊？♥♥ %MASTER_CALL()%、你手没在动…？♥♥\\n　%SELF_CALL()%、不自觉地就在摇腰了…？♥♥」"
 },
 {
  "source": "「なぁ…%SELF_CALL()%って筋肉質でどうも女らしくない身体だよなぁ…\\n「え、えぇ…♥ 褒めてくれるのは%MASTER_CALL()%只是だよ…♥♥」",
  "target": "「喂…%SELF_CALL()%这肌肉结实的身板怎么看都不像个女人啊…\\n「呃、诶…♥ 会夸我的也就只有%MASTER_CALL()%了…♥♥」"
 },
 {
  "source": "\\d%CALLNAME%のお腹は%CALLNAME:0%の子を宿して膨らんでいる…\\d\\n\\n「呼呼♥♥ 腹の赤んぼによしよし、ってしてやってくれよ♥♥」",
  "target": "\\d%CALLNAME%のお腹は%CALLNAME:0%の子を宿して膨らんでいる…\\d\\n\\n「呼呼♥♥ 帮我摸摸肚子里的娃、好好哄哄他啊♥♥」"
 },
 {
  "source": "\\d%CALLNAME%のお腹は%CALLNAME:0%の子を宿して膨らんでいる…\\d\\n\\n「哈啊……妊娠までさせられるとはな……」",
  "target": "\\d%CALLNAME%のお腹は%CALLNAME:0%の子を宿して膨らんでいる…\\d\\n\\n「哈啊……居然连怀孕都让我赶上了啊……」"
 },
 {
  "source": "\\d%CALLNAME%のお腹は%CALLNAME:0%の子を宿して膨らんでいる…\\d\\n\\n「う咕呜…こんな場所で孕まされて……ゆるさねえ…」",
  "target": "\\d%CALLNAME%のお腹は%CALLNAME:0%の子を宿して膨らんでいる…\\d\\n\\n「唔咕呜…在这种地方被搞大肚子……饶不了你…」"
 },
 {
  "source": "「ふぎぃ♥♥ 尻穴セックスとかスパンキングみたいな变态プレイでぇ…♥♥\\n　あんあん喘いで即高潮する身体になっちまったぁ♥♥ んおおぉっ♥♥」",
  "target": "「呼欸♥♥ 被肛交啊打屁股啊这种变态玩法搞的…♥♥\\n　变成光是啊啊叫唤就能马上高潮的身体了♥♥ 嗯哦哦哦っ♥♥」"
 },
 {
  "source": "「啊咿♥♥ 拘束されながら%ANAL_CALL()%犯されて悦んでる变态マゾにぃ♥♥\\n　尻ビンタのご褒美谢谢ございましゅぅ♥♥♥」",
  "target": "「啊咿♥♥ 被绑着还被%ANAL_CALL()%干还爽得不行的变态抖M♥♥\\n　打屁股的奖励真是太感谢了♥♥♥」"
 },
 {
  "source": "「むっちり奶子で%MASTER_CALL()%を抱っこしてやるよ…♥\\n　なんも考えずに…ちゅぱ♥ちゅぱ♥甘えていいからな…♥♥」",
  "target": "「用肉嘟嘟的奶子抱抱%MASTER_CALL()%…♥\\n　啥都不用想…啾噗♥啾噗♥撒个娇也没事…♥♥」"
 },
 {
  "source": "「呵呵…♥ いいこ…いいこ…♥」",
  "target": "「呵呵…♥ 真乖…真乖…♥」"
 },
 {
  "source": "「はは♥ %MASTER_CALL()%♥♥ 甘えんぼだなぁ♥♥♥」",
  "target": "「哈哈♥ %MASTER_CALL()%♥♥ 真是个爱撒娇的家伙啊♥♥♥」"
 },
 {
  "source": "「す、好きで大きくなった訳じゃ…きゃ呜呜嗯♥♥」",
  "target": "「又、又不是我自己想变这么大的…呜嗯♥♥」"
 },
 {
  "source": "「…っ こんなの、恥ずかしいと思わないのかよ……」",
  "target": "「…っ 这种事儿，你就不觉得害臊吗…」"
 },
 {
  "source": "「は呜呜♥ お乳でないってぇ…♥♥ ん啊啊♥♥」",
  "target": "「哈呜呜♥ 都说没奶水了…♥♥ 嗯啊啊♥♥」"
 },
 {
  "source": "「嗯嗯…♥ 強く吸っても出ないって…」",
  "target": "「嗯嗯…♥ 使劲吸也出不来…」"
 },
 {
  "source": "「母乳は出せないから…諦め、ん嗯♥」",
  "target": "「反正也出不来母乳…放弃吧、嗯♥」"
 },
 {
  "source": "「いくら吸っても母乳が出たりしね诶て…っ」",
  "target": "「不管怎么吸母乳也不会出来…っ」"
 },
 {
  "source": "「ん啊啊っ♥ 先っぽ弱点所以ぁ♥♥ レロレロは不行だってぇ♥♥♥」",
  "target": "「嗯啊啊っ♥ 尖尖是弱点的说♥♥ 舔来舔去的可不行啊♥♥♥」"
 },
 {
  "source": "「啊咿嘻…♥ %MASTER_CALL()%の舌…诶ちすぎるぅ♥♥」",
  "target": "「啊咿嘻…♥ %MASTER_CALL()%的舌头…太色了啦♥♥」"
 },
 {
  "source": "「%SWEET_MASTER_CALL()%♥♥ 更加奶子いぢめてぇ♥♥」",
  "target": "「%SWEET_MASTER_CALL()%♥♥ 再欺负欺负奶子嘛♥♥」"
 },
 {
  "source": "「%SWEET_MASTER_CALL()%♥♥ 乳头ねぶりうますぎるって♥♥」",
  "target": "「%SWEET_MASTER_CALL()%♥♥ 你舔乳头技术也太好了吧♥♥」"
 },
 {
  "source": "「啊啊啊♥ 舌で転がされたらぁっ♥♥ 感じすぎて辛いんだってぇ♥♥♥」",
  "target": "「啊啊啊♥ 被舌头这么一拨弄♥♥ 太有感觉了受不了了啊♥♥♥」"
 },
 {
  "source": "「啊啊…♥ %MASTER_CALL()%のおしゃぶり…好舒服…♥♥」",
  "target": "「啊啊…♥ %MASTER_CALL()%的吮吸…好舒服…♥♥」"
 },
 {
  "source": "「哈咿…♥♥ 優しく甘噛みされたら、すげえ有感觉…っ♥♥」",
  "target": "「哈咿…♥♥ 被你这么温柔地轻咬，超级有感觉…っ♥♥」"
 },
 {
  "source": "「はぅ…♥♥ %SELF_CALL()%のちっちゃな奶头…チロチロってされてる…♥♥」",
  "target": "「哈呜…♥♥ %SELF_CALL()%的小奶头…被拨来拨去的…♥♥」"
 },
 {
  "source": "「ん啊啊…♥ 小さい胸にこんなに愛情こめてくれるなんて…♥♥」",
  "target": "「嗯啊啊…♥ 对这么小的胸还倾注这么多…♥♥」"
 },
 {
  "source": "「嗯嗯… ぺろぺろ♥ ちゅぱちゅぱ♥ 好色赤んぼだな…っ♥♥」",
  "target": "「嗯嗯… 舔舔♥ 啾噗啾噗♥ 真是个好色的小鬼啊…っ♥♥」"
 },
 {
  "source": "「わ、わざわざ舌で刺激すんなぁ…っ♥」",
  "target": "「喂、还特意用舌头来刺激啊…っ♥」"
 },
 {
  "source": "「あ呜呜…♥ ねちっこい舌づかい…♥」",
  "target": "「啊呜呜…♥ 这黏糊糊的舌头…♥」"
 },
 {
  "source": "「喂，♥ 乳头が舌で転がされてる…♥」",
  "target": "「喂，♥ 乳头被舌头滚来滚去的…♥」"
 },
 {
  "source": "「咕…胸がねぶられてる…っ」",
  "target": "「咕…胸部被舔着…っ」"
 },
 {
  "source": "「啊哈♥♥ 乳头ねちっこく吸われるのぉ♥♥ やばいぃ♥♥♥」",
  "target": "「啊哈♥♥ 乳头被这么黏糊地吸♥♥ 要命了♥♥♥」"
 },
 {
  "source": "「啊啊…そんなに夢中でしゃぶりついて…♥♥ 乳牛として一番嬉しいんだよなぁ…♥♥」",
  "target": "「啊啊…这么着迷地嘬着…♥♥ 作为乳牛这可是最开心的时候啊…♥♥」"
 },
 {
  "source": "「しゃぶりがいのある母牛奶子♥♥ 思う存分味わってくれよな♥♥」",
  "target": "「值得好好嘬的母牛奶子♥♥ 你可要尽情享用啊♥♥」"
 },
 {
  "source": "「啊啊…♥ こんなに美味そうに飲んでくれるなんて…♥♥」",
  "target": "「啊啊…♥ 喝得这么香…♥♥」"
 },
 {
  "source": "「哎呀♥ そんな诶ちな吸い方…♥ 母乳とまらない♥♥」",
  "target": "「哎呀♥ 那么色的吸法…♥ 母乳停不下来了啊♥♥」"
 },
 {
  "source": "「はぅ…♥ ぷっくり乳头が舐めしゃぶられて、母乳がこぼれてきた…♥♥」",
  "target": "「哈呜…♥ 鼓起来的乳头被舔吸着，母乳都溢出来了…♥♥」"
 },
 {
  "source": "「はぅ…♥ そんなしゃぶり方されたら母乳止まらない……っ♥」",
  "target": "「哈呜…♥ 被那么个吸法母乳根本停不下来……っ♥」"
 },
 {
  "source": "「呜呜… 不要らしく刺激されて母乳がこぼれちまう……♥」",
  "target": "「呜呜… 被不情不愿地刺激着母乳都洒出来了……♥」"
 },
 {
  "source": "「已经出ないけど…おしゃぶり只是でもしてくか…？♥」",
  "target": "「反正也出不来奶了…光嘬着玩总行吧…？♥」"
 },
 {
  "source": "「嘻嘻 そんな赤んぼみたいにされると真的に出ちまう也许…♥」",
  "target": "「嘻嘻 被你这么当小宝宝一样伺候说不定真要出奶了…♥」"
 },
 {
  "source": "「いくら舐め吸吧も母乳が出たりしね诶て…っ」",
  "target": "「不管怎么舔怎么吸母乳也不会出来…っ」"
 },
 {
  "source": "「ぁむっ♥ ちゅる♥ れろ…♥ 哈啊、哈啊♥ %SWEET_MASTER_CALL()%♥ 更多噢♥♥」",
  "target": "「啊呜っ♥ 吸溜♥ 舔舔…♥ 哈啊、哈啊♥ %SWEET_MASTER_CALL()%♥ 再来嘛♥♥」"
 },
 {
  "source": "「喂，♥ ちゅっ♥ 嗯~～♥ 哈啊♥……更加…きすしたい…♥♥」",
  "target": "「喂，♥ 啾っ♥ 嗯~～♥ 哈啊♥……还想…再亲…♥♥」"
 },
 {
  "source": "「ん…♥ ちゅっ…ちゅぱ…♥ %MASTER_CALL()%…♥ ん…っ♥」",
  "target": "「嗯…♥ 啾っ…啾噗…♥ %MASTER_CALL()%…♥ 嗯…っ♥」"
 },
 {
  "source": "「ちゅ♥…ぁむ♥…すき♥…すき♥…嗯♥……ちゅっ♥」",
  "target": "「啾♥…啊呜♥…喜欢♥…喜欢♥…嗯♥……啾っ♥」"
 },
 {
  "source": "「ん…っ ふっ…嗯嗯…っ♥」",
  "target": "「嗯…っ 呼…嗯嗯…っ♥」"
 },
 {
  "source": "「ん嗯！ ぐ…っ そのうち舌を噛み切ったる…っ」",
  "target": "「嗯！ 咕…っ 早晚把你舌头咬断…っ」"
 },
 {
  "source": "「啊♥ 啊♥ 啊♥ 舌で転がされてっ♥♥」",
  "target": "「啊♥ 啊♥ 啊♥ 被舌头滚着弄♥♥」"
 },
 {
  "source": "「あぅっ♥ 舐められる度に身体が跳ねるぅ♥♥」",
  "target": "「啊呜っ♥ 每次被舔身体都会弹起来♥♥」"
 },
 {
  "source": "「だ、駄目だってっ♥ そこ敏感で…ん嗯♥♥」",
  "target": "「都、都说了不行っ♥ 那里敏感…嗯嗯♥♥」"
 },
 {
  "source": "「咕呜♥ …%MASTER_CALL()%なんかにされて有感觉わけ……」",
  "target": "「咕呜♥ …被%MASTER_CALL()%这种人搞会有感觉才怪……」"
 },
 {
  "source": "「哈嗯♥ %MASTER_CALL()%に舐めさせるなんて、背徳感厉害ぃ♥♥」",
  "target": "「哈嗯♥ 让%MASTER_CALL()%给我舔什么的，背德感太强了♥♥」"
 },
 {
  "source": "「啊啊…♥ 诶ちな汁で%MASTER_CALL()%の顔がベトベトじゃんかぁ…♥♥」",
  "target": "「啊啊…♥ 用色色的汁把%MASTER_CALL()%的脸弄得黏糊糊的呢…♥♥」"
 },
 {
  "source": "「あぅぅ…♥ そこ…汚いってばぁ♥」",
  "target": "「啊呜…♥ 都说了那地方脏了…♥」"
 },
 {
  "source": "「呜呜っ…♥ そんな所…駄目だって…」",
  "target": "「呜呜…♥ 都说那种地方不行了…」"
 },
 {
  "source": "「はぅぅ♥ %SELF_CALL()%の一番恥ずかしい所がねぶられてるぅ♥♥」",
  "target": "「哈呜♥ %SELF_CALL()%最羞人的地方被舔着呢♥♥」"
 },
 {
  "source": "「そ、そんな地方舐めるなんて…どうかしてる…っ」",
  "target": "「舔、舔那种地方…你脑子有问题吧…」"
 },
 {
  "source": "「喂，♥ 入口の周りを舌でなぞられて…♥♥」",
  "target": "「喂，♥ 用舌头在入口周围打转…♥♥」"
 },
 {
  "source": "「啊啊啊♥ 舌で%ANAL_CALL()%がほじられてるぅ♥♥」",
  "target": "「啊啊啊♥ 舌头在挖%ANAL_CALL()%呢♥♥」"
 },
 {
  "source": "「啊啊ぁぁ…… %ANAL_CALL()%がヒクヒクしてる所、観察すんなってぇ…♥♥」",
  "target": "「啊啊啊……别盯着%ANAL_CALL()%一抽一抽的看啊…♥♥」"
 },
 {
  "source": "「%SWEET_MASTER_CALL()%… は、恥ずかしくて死にそう…っ♥♥」",
  "target": "「%SWEET_MASTER_CALL()%… 羞、羞死人了…♥♥」"
 },
 {
  "source": "「～～っ！ ぴちゃぴちゃ音立てんなぁ♥♥」",
  "target": "「～～っ！ 别发出那种啪嗒啪嗒的水声啊♥♥」"
 },
 {
  "source": "「啊—…♥♥ その舌の動きやばいぃ…♥♥」",
  "target": "「啊—…♥♥ 那舌头的动作太要命了…♥♥」"
 },
 {
  "source": "「ほぉぉっ♥♥ 舌の動きに合わせて腰ヘコ止まんない…っ♥♥」",
  "target": "「呼哦哦♥♥ 跟着舌头的动作腰根本停不下来…♥♥」"
 },
 {
  "source": "「哦♥ 哦♥ %ANAL_CALL()%がパクパクおねだりしちゃってるっ♥♥」",
  "target": "「哦♥ 哦♥ %ANAL_CALL()%一张一合地在讨要呢♥♥」"
 },
 {
  "source": "「哈啊♥…哈啊♥……な、なぁ…已经十分だろ…？\n　はやく%ANAL_CALL()%着%PENIS_CALL()%くれよぉ…♥♥」",
  "target": "「哈啊♥…哈啊♥……喂、喂…已经够了吧…？\n　快把%PENIS_CALL()%插进%ANAL_CALL()%啊…♥♥」"
 },
 {
  "source": "「んおぉ…♥♥ %ANAL_CALL()%が舌でトロトロにほぐされてるぅ…♥♥」",
  "target": "「嗯哦…♥♥ %ANAL_CALL()%被舌头舔得软成一团了…♥♥」"
 },
 {
  "source": "「呜呜…♥ 子供らしいキレイな%ANAL_CALL()%とかゆーな…っ♥♥」",
  "target": "「呜呜…♥ 别说像小孩子一样漂亮的%ANAL_CALL()%这种话…♥♥」"
 },
 {
  "source": "「あぅぅ…♥ そんな地方…は、恥ずかしい…」",
  "target": "「啊呜…♥ 那种地方…太羞人了…」"
 },
 {
  "source": "「ひぅ…へ、变态……」",
  "target": "「咿…变、变态……」"
 },
 {
  "source": "「啊呜♥ %MASTER_CALL()%、くすぐったいってぇ♥♥」",
  "target": "「啊呜♥ %MASTER_CALL()%、都说痒了♥♥」"
 },
 {
  "source": "「喂，♥ ふわふわたぷたぷのマシュマロ♥ 気に入ったか？♥♥」",
  "target": "「喂，♥ 这软乎乎胖嘟嘟的棉花糖♥ 满意了？♥♥」"
 },
 {
  "source": "「呵呵…♥ 柔らかいパン生地みたいで美味そうだろ？♥♥」",
  "target": "「呵呵…♥ 像软面包似的看起来很好吃吧？♥♥」"
 },
 {
  "source": "「はぅぅ…♥ わざと乳头を避けて焦らされてるぅ♥♥」",
  "target": "「哈呜…♥ 故意避开乳头撩我…♥♥」"
 },
 {
  "source": "「ん嗯…動物みたいになるくらい胸が好きなんだな…」",
  "target": "「嗯嗯…就那么喜欢奶子吗跟个野兽似的…」"
 },
 {
  "source": "「呜呜……なんつーか变态的だぜ…」",
  "target": "「呜呜…该说你变态呢还是啥的…」"
 },
 {
  "source": "「ん哈啊…♥ 甘噛み…♥ 癖になりそうだ…♥♥」",
  "target": "「嗯哈啊…♥ 轻咬…♥ 都快上瘾了…♥♥」"
 },
 {
  "source": "「は咿♥ 舌でなぞられるとゾクゾクする…っ♥♥」",
  "target": "「哈咿♥ 被舌头一舔整个人都麻了…♥♥」"
 },
 {
  "source": "「ひゃうっ！ …耳は弱いから…やめ…っ！」",
  "target": "「呀呜っ！…耳朵怕痒…别…！」"
 },
 {
  "source": "「ひぅ…においの強い地方、好きなのか…？♥」",
  "target": "「咿…你喜欢味道重的地方…？♥」"
 },
 {
  "source": "「あ、汗もかいてるし、恥ずかしいって…♥」",
  "target": "「啊、还出了汗、多不好意思啊…♥」"
 },
 {
  "source": "「呜呜…♥ 恥ずかしがらせて愉しむなんて……ひでえヤツ…♥」",
  "target": "「呜呜…♥ 就爱看我出丑是吧……你这混蛋…♥」"
 },
 {
  "source": "「呜呜…は、恥ずかしい……やめてくれって…」",
  "target": "「呜呜…好、好丢人……都说了停下…」"
 },
 {
  "source": "「そんな地方…き、汚いと思うけど…」",
  "target": "「那种地方…我、我觉得脏啊…」"
 },
 {
  "source": "「呼呼♥ くすぐったいって…♥」",
  "target": "「呼呼♥ 都说痒了…♥」"
 },
 {
  "source": "「おぉ♥♥ ずいぶん情熱的だな♥♥」",
  "target": "「哦哦♥♥ 还挺热情的嘛♥♥」"
 },
 {
  "source": "「んふー♥ 愛玩ペットの%CALLNAME%は、飼い主からのペロペロが大好きだぞぉ♥♥」",
  "target": "「嗯呼♥ 宠物%CALLNAME%最喜欢主人的舔舔了哦♥♥」"
 },
 {
  "source": "「へへ♥ 独占欲ってやつかぁ…？♥」",
  "target": "「嘿嘿♥ 这就是占有欲吗…？♥」"
 },
 {
  "source": "「呜呜っ…顔を汚すのはやめてほしい…」",
  "target": "「呜呜…别弄脏我的脸…」"
 },
 {
  "source": "「ひ呜呜っ…や、やめてくれ……呜呜ぅ…」",
  "target": "「咿呜呜…住、住手啊……呜呜呜…」"
 },
 {
  "source": "「啊啊…♥ ここまでさせるなら、いっそ初めてを奪ってくれよ…♥」",
  "target": "「啊啊…♥ 都让我做到这份上了、不如干脆拿走我的第一次算了…♥」"
 },
 {
  "source": "「呵呵…♥ %MASTER_CALL()%はこーゆープレイも好きなのか♥♥」",
  "target": "「呵呵…♥ %MASTER_CALL()%也好这口吗♥♥」"
 },
 {
  "source": "「こういうプレイが好きなんだな…」",
  "target": "「你原来喜欢这种玩法啊…」"
 },
 {
  "source": "「ま、まぁ…入れられるよりマシか………」",
  "target": "「嘛、嘛…总比被插进去强吧……」"
 },
 {
  "source": "「啊啊…♥ %VAGINA_CALL()%焦らされて切なくなってきた…♥♥」",
  "target": "「啊啊…♥ %VAGINA_CALL()%被吊着胃口好难受…♥♥」"
 },
 {
  "source": "「はぅ…♥ クリが擦れて好舒服…♥♥」",
  "target": "「哈呜…♥ 阴蒂蹭着好舒服…♥♥」"
 },
 {
  "source": "「呵呵…♥ %SELF_CALL()%のお汁で%PENIS_CALL()%がヌルヌルになっちまったな♥♥」",
  "target": "「呵呵…♥ %PENIS_CALL()%被%SELF_CALL()%的汁水弄得滑溜溜的了♥♥」"
 },
 {
  "source": "「へへっ♥ %SELF_CALL()%の小さい身体じゃ%PENIS_CALL()%に跳ね飛ばされそうだな♥」",
  "target": "「嘿嘿♥ %SELF_CALL()%这小身板都要被%PENIS_CALL()%弹飞了呢♥」"
 },
 {
  "source": "「嗯…嗯…♥ へ、変な気持ちになりそう…♥」",
  "target": "「嗯…嗯…♥ 要、要有种奇怪的感觉了…♥」"
 },
 {
  "source": "「嗯♥ ふっ…ん嗯♥」",
  "target": "「嗯♥ 呼…嗯嗯♥」"
 },
 {
  "source": "「ん…♥ おしゃぶりご奉仕、してやるよ♥♥」",
  "target": "「嗯…♥ 给你来个口活服务吧♥♥」"
 },
 {
  "source": "「ちゅっ♥ れろっ♥ …いっぱい口呢やっから楽にしてていいぜ♥♥」",
  "target": "「啾♥ 舔♥ ……会好好用嘴伺候你的、你只管放松就行♥♥」"
 },
 {
  "source": "「はむっ♥ ちゅるっ れろれろれろっ♥ ちゅっ♥ ちゅっ♥\n　%SELF_CALL()%の本気汁で汚れた%PENIS_CALL()%♥♥ 念入りに掃除しないと…♥♥」",
  "target": "「含住♥ 吸溜 舔舔舔舔♥ 啾♥ 啾♥\n　被%SELF_CALL()%的真情汁弄脏的%PENIS_CALL()%♥♥ 不仔细清理可不行…♥♥」"
 },
 {
  "source": "「はむっ♥ ちゅるっ れろれろれろっ♥ ちゅっ♥ ちゅっ♥\n　%SELF_CALL()%的%ANAL_CALL()%で汚れた%PENIS_CALL()%♥♥ 念入りに掃除しないと…♥♥」",
  "target": "「含住♥ 吸溜 舔舔舔舔♥ 啾♥ 啾♥\n　被%SELF_CALL()%的%ANAL_CALL()%弄脏的%PENIS_CALL()%♥♥ 不仔细清理可不行…♥♥」"
 },
 {
  "source": "「はむっ♥ ちゅるっ れろれろれろっ♥ ちゅっ♥ ちゅっ♥\n　精液でどろどろの%PENIS_CALL()%♥♥ 念入りに掃除しないと…♥♥」",
  "target": "「含住♥ 吸溜 舔舔舔舔♥ 啾♥ 啾♥\n　被精液弄得黏糊糊的%PENIS_CALL()%♥♥ 不仔细清理可不行…♥♥」"
 },
 {
  "source": "「呜呜…命令ならしかたねえ…」",
  "target": "「呜呜…既然是命令那也没辙…」"
 },
 {
  "source": "「うぐ、咕呜っ……こ、こんなモンを口に……」",
  "target": "「唔、咕呜……这、这种东西要放进嘴里……」"
 },
 {
  "source": "「ぢゅぱっ♥ ぢゅぱっ♥ じゅるるる……ぢゅぽっ♥\\n　…%MASTER_CALL()%♥ おくち飞机杯、好舒服か♥♥」",
  "target": "「ぢゅぱっ♥ ぢゅぱっ♥ じゅるるる……ぢゅぽっ♥\\n　…%MASTER_CALL()%♥ 小嘴飞机杯、舒服吗♥♥」"
 },
 {
  "source": "「んむっ♥ じゅるっ♥ じゅぷっ♥ ぁむ♥ んぶっ…♥\\n　…ぷ哈啊♥ %MASTER_CALL()%的%PENIS_CALL()%の味♥ 好き也许♥♥」",
  "target": "「んむっ♥ じゅるっ♥ じゅぷっ♥ ぁむ♥ んぶっ…♥\\n　…噗哈啊♥ %MASTER_CALL()%的%PENIS_CALL()%的味道♥ 也许喜欢♥♥」"
 },
 {
  "source": "「先っぽあたりをチロチロ…♥ってされるの好きだよな♥♥」",
  "target": "「龟头附近被那样舔来舔去…♥你这家伙很喜欢吧♥♥」"
 },
 {
  "source": "「ふむっ♥…れろっ♥…ぁむっ♥…」\\n（拘束されて口只是動かして…まさに性処理ペットだなぁ♥♥）",
  "target": "「ふむっ♥…れろっ♥…ぁむっ♥…」\\n（被绑着嘴巴只能动…简直是性处理宠物啊♥♥）"
 },
 {
  "source": "「嗯♥…ちゅる…じゅぷっ♥…ぁむ♥……ちゅっ♥」\\n（%MASTER_CALL()%、気持ちよさそうな顔…♥ よかった…嬉しい…♥）",
  "target": "「嗯♥…ちゅる…じゅぷっ♥…ぁむ♥……ちゅっ♥」\\n（%MASTER_CALL()%、一脸舒服的表情…♥ 太好了…好开心…♥）"
 },
 {
  "source": "「れろ♥ ちゅっ♥ ちゅるる…ちゅぱっ♥ ぷは…♥\\n　%MASTER_CALL()%的%PENIS_CALL()%苦しそう…すぐに良くしてやっからな…♥」",
  "target": "「れろ♥ ちゅっ♥ ちゅるる…ちゅぱっ♥ ぷは…♥\\n　%MASTER_CALL()%的%PENIS_CALL()%看着挺难受…老子马上让你舒服起来…♥」"
 },
 {
  "source": "「ん…♥ ぁむ…♥ れろ…♥ 玉のほうも……ん…やさしく舐めてやるから…♥」",
  "target": "「ん…♥ ぁむ…♥ れろ…♥ 玉的那边也……ん…老子会温柔地舔的…♥」"
 },
 {
  "source": "「ちゅぽっ♥…ぢゅるっ♥…ずぞっ♥…ぢゅぽっ♥…」\\n（呜呜…ひょっとこ顔、まじまじと見られて…恥ずかしすぎる…）",
  "target": "「ちゅぽっ♥…ぢゅるっ♥…ずぞっ♥…ぢゅぽっ♥…」\\n（呜呜…做鬼脸的样子被死死盯着…太他妈羞人了…）"
 },
 {
  "source": "「れろ…♥ ちゅぷ…♥ ん…カリの所に垢が……嗯…ぢゅるるるっ♥♥」\\n（どん只是臭くて汚くても%MASTER_CALL()%のならへーき…♥♥）",
  "target": "「れろ…♥ ちゅぷ…♥ ん…カリ的沟里有垢……嗯…ぢゅるるるっ♥♥」\\n（就算再臭再脏只要是%MASTER_CALL()%的就没问题…♥♥）"
 },
 {
  "source": "「嗯…ぁむ…ど、どうだよ…」",
  "target": "「嗯…ぁむ…怎、怎么样啊…」"
 },
 {
  "source": "（先っぽ…反応がいいみたいだな…）",
  "target": "（龟头…反应好像不错啊…）"
 },
 {
  "source": "「うぐっ…嗯…ん嗯…ふぐっ…」",
  "target": "「うぐっ…嗯…ん嗯…ふぐっ…」"
 },
 {
  "source": "（ぐ呜呜…血管が浮いて気持ち悪いし、ひでえにおい…）",
  "target": "（咕呜呜…青筋暴起恶心死了、味道也够呛…）"
 },
 {
  "source": "「ああ、%MASTER_CALL()%♥♥ 奶子呢欲しいんだな♥♥」",
  "target": "「啊啊、%MASTER_CALL()%♥♥ 想要奶子呢是吧♥♥」"
 },
 {
  "source": "「%MASTER_CALL()%♥ %SELF_CALL()%の胸でいっぱい気持ちよくなってくれよ♥♥」",
  "target": "「%MASTER_CALL()%♥ 用%SELF_CALL()%的胸好好爽一把吧♥♥」"
 },
 {
  "source": "「へへっ♥ %MASTER_CALL()%的%PENIS_CALL()%、奶子で捕まえちまった♥♥」",
  "target": "「嘿嘿っ♥ %MASTER_CALL()%的%PENIS_CALL()%、被奶子逮住了呢♥♥」"
 },
 {
  "source": "「%MASTER_CALL()%♥ 『小さいのに大きい』…なんてのも好きだろ？♥♥」",
  "target": "「%MASTER_CALL()%♥ 『小却大』…这种你也好这口吧？♥♥」"
 },
 {
  "source": "「小さくても、その分たっぷり動いて奉仕するからな♥♥」",
  "target": "「就算小、也会拼命好好动起来伺候你的♥♥」"
 },
 {
  "source": "「なぁなぁ♥ 子供っぽいペタンコの胸但是、そんなのも好きなんだよな？♥♥」",
  "target": "「喂喂♥ 像小孩一样平坦的胸但是、你也好这口的对吧？♥♥」"
 },
 {
  "source": "「う…わかったよ…」",
  "target": "「呃…知道了啦…」"
 },
 {
  "source": "「嘻嘻 柔らかい乳肉がたっぷり詰まった自慢のパイズリ飞机杯…♥♥\\n　まさに%PENIS_CALL()%にとっての極楽だろ？♥♥」",
  "target": "「嘻嘻 柔软的乳肉塞得满满的自豪乳交飞机杯…♥♥\\n　对%PENIS_CALL()%来说简直是极乐世界吧？♥♥」"
 },
 {
  "source": "「はふぅ♥ %MASTER_CALL()%的%PENIS_CALL()%をしごく為に育った奶子♥♥\\n　頑張って気持ちよくするからご褒美ザーメンいっぱい欲しい♥♥」",
  "target": "「はふぅ♥ %MASTER_CALL()%的%PENIS_CALL()%就是为榨取而长出来的奶子♥♥\\n　老子会努力让你舒服的所以奖励精液给多多的♥♥」"
 },
 {
  "source": "「嗯~？♥ たぷんたぷん動く奶子に、目が釘付けじゃねぇかぁ♥♥」",
  "target": "「嗯~？♥ 被扑通扑通晃动的奶子、眼睛都看直了不是嘛♥♥」"
 },
 {
  "source": "「ん嗯♥♥ たっぷり育った乳牛奶子♥♥ 喜んでもらえてうれしいよ♥♥」",
  "target": "「ん嗯♥♥ 好好发育长大的乳牛奶子♥♥ 你能开心老子也高兴啊♥♥」"
 },
 {
  "source": "「嗯嗯…♥ 薄い胸に興奮するなんて、ヘンなヤツ…♥♥」",
  "target": "「嗯嗯…♥ 对贫乳都能兴奋、真是个怪胎…♥♥」"
 },
 {
  "source": "「嗯♥♥ %MASTER_CALL()%♥ 更加早くするからな♥♥」",
  "target": "「嗯♥♥ %MASTER_CALL()%♥ 老子会再快点的♥♥」"
 },
 {
  "source": "「ん嗯♥♥ たっぷり育った奶子♥♥ 喜んでもらえてうれしいよ♥♥」",
  "target": "「ん嗯♥♥ 好好发育长大的奶子♥♥ 你能开心老子也高兴啊♥♥」"
 },
 {
  "source": "「ふぅ…ふぅ…%PENIS_CALL()%が固くて……厉害…」",
  "target": "「呼…呼…%PENIS_CALL()%好硬……厉害…」"
 },
 {
  "source": "「す、好きで大きくなった訳じゃ…きゃ呜呜嗯♥」",
  "target": "「又、又不是老子自己想长这么大的…呀呜呜嗯♥」"
 },
 {
  "source": "「呜呜…胸をこんなことに使うなんて……」",
  "target": "「呜呜…竟然把胸用在这种事上……」"
 },
 {
  "source": "「ふっ…嗯…薄い胸に擦られて何が楽しいんだか…」",
  "target": "「哼…嗯…被贫乳蹭来蹭去有什么好爽的…」"
 },
 {
  "source": "「あ嗯♥……強引なのもイイ也许♥♥」",
  "target": "「啊嗯♥……强硬一点的也不错呢也许♥♥」"
 },
 {
  "source": "「やぁ嗯♥♥ %MASTER_CALL()%に襲われるぅ♥♥」",
  "target": "「呀啊嗯♥♥ 被%MASTER_CALL()%袭击了♥♥」"
 },
 {
  "source": "「呜呜…乱暴はすんなっての……」",
  "target": "「呜呜…说了别这么粗暴……」"
 },
 {
  "source": "「ぐっ…こんなモン、擦りつけんな…っ」",
  "target": "「呃…别拿这种玩意儿蹭过来…っ」"
 },
 {
  "source": "「啊♥ 啊♥ 乱暴にされて感じちまうっ♥♥ ん啊啊っ♥♥♥」",
  "target": "「啊♥ 啊♥ 被粗暴对待反而有感觉了っ♥♥ ん啊啊っ♥♥♥」"
 },
 {
  "source": "「哈咿♥♥ %SWEET_MASTER_CALL()%♥♥ 激しくされるの好舒服っ♥♥♥」",
  "target": "「哈咿♥♥ %SWEET_MASTER_CALL()%♥♥ 被激烈对待好爽っ♥♥♥」"
 },
 {
  "source": "「啊啊♥♥ %MASTER_CALL()%が腰を打ちつける度にパンパン鳴って…♥♥\\n　なんか真的にセックスしてるみたいだ…♥♥」",
  "target": "「啊啊♥♥ 每次%MASTER_CALL()%挺腰撞上来都啪啪作响…♥♥\\n　感觉真像在做爱一样…♥♥」"
 },
 {
  "source": "「啊♥ はしたないメス牛奶子♥ 更加躾けてくれえ♥♥♥」",
  "target": "「啊♥ 下贱的母牛奶子♥ 再好好调教老子吧♥♥♥」"
 },
 {
  "source": "「ぁ嗯♥ この大奶子飞机杯、乱暴にされると悦ぶからさ…♥♥\\n　啊♥ 啊啊っ♥ 思い切り腰をぶつけて愉しんでくれよ♥♥」",
  "target": "「ぁ嗯♥ 这对大奶子飞机杯、被粗暴对待就发情…♥♥\\n　啊♥ 啊啊っ♥ 尽管用力挺腰撞上来好好享受吧♥♥」"
 },
 {
  "source": "「は咿♥ は咿♥ 奶子レイプされるのたまんねぇ…っ♥♥」",
  "target": "「哈咿♥ 哈咿♥ 奶子被强奸真受不了…っ♥♥」"
 },
 {
  "source": "「んぃっ♥ 胸をぎゅぅって掴まれて、%PENIS_CALL()%しごく道具にされてるっ♥♥」",
  "target": "「んぃっ♥ 胸被死死抓住、成了给%PENIS_CALL()%榨取的工具っ♥♥」"
 },
 {
  "source": "「嗯♥♥ %SELF_CALL()%の胸でいっぱい気持ちよくなってくれな♥♥」",
  "target": "「嗯♥♥ 用%SELF_CALL()%的胸让你好好爽一把吧♥♥」"
 },
 {
  "source": "「嗯啊♥ 不要らしく育った大奶子に思い切り欲望をぶつけてくれよ♥♥」",
  "target": "「嗯啊♥ 朝不像话地长大的大奶子尽情发泄欲望吧♥♥」"
 },
 {
  "source": "「んぃっ♥ 胸をぎゅぅっと掴まれて、%PENIS_CALL()%しごく道具にされてるっ♥♥」",
  "target": "「んぃっ♥ 胸被死死抓住、成了给%PENIS_CALL()%榨取的工具っ♥♥」"
 },
 {
  "source": "「嗯…咕呜……乱暴にすんなっての…」",
  "target": "「嗯…咕呜……说了别这么粗暴…」"
 },
 {
  "source": "「ふっ…嗯…薄い胸に擦りつけて何が楽しいんだか…」",
  "target": "「哼…嗯…往贫乳上蹭来蹭去有什么好爽的…」"
 },
 {
  "source": "「『ゆかおな』…？ 意味はわかんねえけど、どうせ良い意味じゃないんだろ」",
  "target": "「『ゆかおな』…？ 啥意思老子是不知道啦、反正肯定不是好话吧」"
 },
 {
  "source": "「まかしときな、%MASTER_CALL()%♥♥」",
  "target": "「交给老子吧、%MASTER_CALL()%♥♥」"
 },
 {
  "source": "「そ、そんなモンに触れって…っ」",
  "target": "「让、让老子碰那种玩意儿…っ」"
 },
 {
  "source": "「なんかオナニーの手伝いしてるみたいでドキドキする♥♥」",
  "target": "「总感觉像是在帮你打飞机一样心跳加速♥♥」"
 },
 {
  "source": "「へへ…透明のつゆが滲んできてんぞ♥♥」",
  "target": "「嘿嘿…透明的汁液渗出来了哟♥♥」"
 },
 {
  "source": "「玉のほうも優しくもみもみ…♥ …%PENIS_CALL()%がビクビク気持ちよさそうじゃ嗯♥♥」",
  "target": "「玉的那边也温柔地揉揉…♥ …%PENIS_CALL()%一抽一抽的挺爽的不是嗯♥♥」"
 },
 {
  "source": "「なんか滲んできて…ヌルヌルしてきた…」",
  "target": "「总觉得渗出来了…变得滑溜溜的了…」"
 },
 {
  "source": "「更加激しく…？ い、痛くねえのか…？」",
  "target": "「更加激烈…？你、你不疼吗…？」"
 },
 {
  "source": "「時どきピクンと跳ねて、なんか不要啊…」",
  "target": "「时不时会突然抽搐一下，总觉得不要啊…」"
 },
 {
  "source": "「奶子吸いながら気持ちよくしてほしいとかさ…♥\\n　%MASTER_CALL()%は欲張り但是素直なヤツだ♥♥」",
  "target": "「一边吸奶子一边还想让老子弄舒服什么的…♥\\n　%MASTER_CALL()%虽然贪心但还挺坦率的嘛♥♥」"
 },
 {
  "source": "「ったく、こんな小さい子に甘えたいとか…%MASTER_CALL()%はけしからんヤツだな♥♥」",
  "target": "「真是的，还想跟这么小的孩子撒娇…%MASTER_CALL()%你这家伙真不像话啊♥♥」"
 },
 {
  "source": "「子供っぽいペタンコの胸但是、そんなのも好きなんだよな？♥♥」",
  "target": "「像小孩一样的扁平胸，但你就喜欢这种的对吧？♥♥」"
 },
 {
  "source": "「ほら%MASTER_CALL()%…♥ たっぷり癒してやるからな…♥♥」",
  "target": "「喂%MASTER_CALL()%…♥ 老子会好好给你治愈的…♥♥」"
 },
 {
  "source": "「さぁ…全身の力を抜いて…♥ 身体を%SELF_CALL()%に預けな♥♥」",
  "target": "「来…全身放松…♥ 把身体交给%SELF_CALL()%吧♥♥」"
 },
 {
  "source": "「嘻嘻 %SELF_CALL()%の胸で埋もれちまったな♥♥」",
  "target": "「嘻嘻 整个脸都埋在%SELF_CALL()%的胸口里了♥♥」"
 },
 {
  "source": "「嘻嘻 %SELF_CALL()%の胸で顔が埋もれちまったな♥♥」",
  "target": "「嘻嘻 脸都埋在%SELF_CALL()%的胸口里了♥♥」"
 },
 {
  "source": "「嘻嘻 胸は小ぶり但是、嫌いじゃないよな♥♥」",
  "target": "「嘻嘻 胸虽然小了点，但也不讨厌吧♥♥」"
 },
 {
  "source": "「なんつーか…赤んぼの真似がサマになりすぎじゃねえの……」",
  "target": "「该怎么说…你这装婴儿也太像样了吧……」"
 },
 {
  "source": "「うわ……变态的だな…」",
  "target": "「呜哇……真变态啊…」"
 },
 {
  "source": "「%MASTER_CALL()%♥ 奶子しゃぶりながらシコシコされるの、感觉ーだろ♥♥」",
  "target": "「%MASTER_CALL()%♥ 一边吸奶子一边被撸，很爽吧♥♥」"
 },
 {
  "source": "「よしよし%MASTER_CALL()%♥♥ いっぱい甘やかしてやっからな♥♥」",
  "target": "「好啦好啦%MASTER_CALL()%♥♥ 老子会好好宠你的♥♥」"
 },
 {
  "source": "「啊啊…♥ %MASTER_CALL()%とこんなにいちゃいちゃ出来るなんてさ…♥♥♥」",
  "target": "「啊啊…♥ 能跟%MASTER_CALL()%这样亲热…♥♥♥」"
 },
 {
  "source": "「喂，♥ そんなに乳头をねぶられたら、%SELF_CALL()%ばっか気持ちよくなっちまうからぁ♥♥」",
  "target": "「喂，♥ 乳头被那样舔的话，不就光让%SELF_CALL()%一个人爽了吗♥♥」"
 },
 {
  "source": "「ほかほか奶子の布団にくるまって…心まで啊たまろうな♥♥」",
  "target": "「裹在热乎乎的奶子被子里…连心都一起暖起来吧♥♥」"
 },
 {
  "source": "「啊—啊—、%MASTER_CALL()%…♥♥ でっかい胸に甘えるの…癖になっちまう也许な♥♥」",
  "target": "「啊—啊—、%MASTER_CALL()%…♥♥ 跟大胸撒娇…怕是要上瘾了吧♥♥」"
 },
 {
  "source": "「嘻嘻 %SELF_CALL()%にも%MASTER_CALL()%の乳汁、ご馳走してくれよな♥♥」",
  "target": "「嘻嘻 %SELF_CALL()%也想尝尝%MASTER_CALL()%的乳汁啊♥♥」"
 },
 {
  "source": "「は呜呜♥ いっぱいシコシコするからぁ♥♥ 更加母乳吸ってほしいぃ♥♥」",
  "target": "「哈呜呜♥ 老子会使劲撸的♥♥ 更想让伱吸母乳啊♥♥」"
 },
 {
  "source": "「啊♥ 授乳好舒服っ♥♥ %MASTER_CALL()%もいっぱい気持ちよくなってくれなぁ♥♥」",
  "target": "「啊♥ 授乳好舒服っ♥♥ %MASTER_CALL()%也要好好享受啊♥♥」"
 },
 {
  "source": "「よしよし♥……いいこ♥…いいこ♥」",
  "target": "「好啦好啦♥……乖孩子♥…乖孩子♥」"
 },
 {
  "source": "「嘻嘻 頭なでなで…安心するか…？♥♥」",
  "target": "「嘻嘻 摸摸头…安心了吗…？♥♥」"
 },
 {
  "source": "「…す、少しくらい恥ずかしいと思えよぉ……」",
  "target": "「…你、你就不会觉得有点羞耻吗……」"
 },
 {
  "source": "「喂，♥ あれもこれもって欲張りなヤツだな…」",
  "target": "「喂，♥ 这也想要那也想要的，真是个贪心的家伙…」"
 },
 {
  "source": "「啊啊…その触手…♥ まさかそんなモンで胸を責められたらぁ…♥♥」",
  "target": "「啊啊…那触手…♥ 没想到被那玩意弄胸的话…♥♥」"
 },
 {
  "source": "「そ、それ……まさかそんなモンを胸に…」",
  "target": "「那、那东西……没想到要把那玩意放在胸上…」"
 },
 {
  "source": "「っ…確かその触手は……奶子を滅茶苦茶に気持ちよくするヤバいヤツだ…♥♥」",
  "target": "「啧…那触手确实是……能把奶子搞得爽翻天的危险玩意儿…♥♥」"
 },
 {
  "source": "「咿…そ、それ…また胸を滅茶苦茶にするつもりで……」",
  "target": "「咿…那、那东西…又要来把胸搞得一团糟吧……」"
 },
 {
  "source": "「目隠しでよくわかんねぇけど、なんかイヤな予感が…」",
  "target": "「蒙着眼睛看不太清楚，但总觉得有种不好的预感…」"
 },
 {
  "source": "「おお゛ぉぉっ♥♥ むりやり被弄到去てっ♥♥ 乳汁噴き出るっ♥♥ んお゛おおぉぉぉっ♥♥」",
  "target": "「哦哦哦っ♥♥ 被强行弄到去了♥♥ 乳汁喷出来了♥♥ 嗯哦哦哦哦っ♥♥」"
 },
 {
  "source": "「哈咿♥♥ 奶子っ♥♥ いぢめちゃ不行ぇ♥♥ んい゛いいぃぃっ♥♥」",
  "target": "「哈咿♥♥ 奶子っ♥♥ 不可以欺负啦♥♥ 嗯咿咿咿咿っ♥♥」"
 },
 {
  "source": "「ほ咿♥ ほ咿♥ じ、自分でも知らないっ は咿♥ 弱点あぶり出されてるっ♥♥♥」",
  "target": "「嚯咿♥ 嚯咿♥ 连、连我自己都不知道的 哈咿♥ 弱点被暴露出来了♥♥♥」"
 },
 {
  "source": "「ん啊啊♥♥ し、振動させながら入れるの不行ぇ♥♥」",
  "target": "「嗯啊啊♥♥ 一、一边振动一边放进去不行啊♥♥」"
 },
 {
  "source": "「嗯嗯♥ そんなモン、入れんじゃ――んいぃっ！？♥♥」",
  "target": "「嗯嗯♥ 那种东西、怎么能放——嗯咿っ！？♥♥」"
 },
 {
  "source": "「あ゛っ♥ あ゛っ♥ オモチャで無理やり感じさせられてるっ♥♥」",
  "target": "「啊っ♥ 啊っ♥ 被玩具强行弄出感觉了♥♥」"
 },
 {
  "source": "「お、お、おぉぉ♥♥ 偽モンの%PENIS_CALL()%でっ♥ 恥ずかしく喘いじま呜呜♥♥」",
  "target": "「哦、哦、哦哦♥♥ 被假货的%PENIS_CALL()%♥ 羞耻地呻吟出来了呜呜♥♥」"
 },
 {
  "source": "「は咿♥ は咿♥ し、振動に合わせて腰がヘコヘコ動いて恥ずかしいっ♥♥」",
  "target": "「哈咿♥ 哈咿♥ 腰随着振动不由自主地晃来晃去好丢脸♥♥」"
 },
 {
  "source": "「んおぉぉ♥♥ 前後両方に入れられて圧迫感やばいぃ♥♥♥」",
  "target": "「嗯哦哦♥♥ 前后都被插入了压迫感好强♥♥♥」"
 },
 {
  "source": "「こ、こんな無理やりっ♥♥ 感じたくないぃ♥♥」",
  "target": "「这、这样强行来♥♥ 我不想有感觉啊♥♥」"
 },
 {
  "source": "「イ、イ咕♥ 強引に高潮させられるっ♥♥」",
  "target": "「要、要去了咕♥ 被强迫高潮了♥♥」"
 },
 {
  "source": "「こ、こんなモンでぇ♥♥ 啊♥ 啊♥ 啊♥」",
  "target": "「用、用这种东西♥♥ 啊♥ 啊♥ 啊♥」"
 },
 {
  "source": "「ふ咕呜♥♥ ぬ、抜けってばぁ…♥♥」",
  "target": "「呼咕呜♥♥ 叫、叫你拔出来啊…♥♥」"
 },
 {
  "source": "「はーっ♥ はーっ♥ 精液こぼれないよう%ANAL_CALL()%に栓されたぁ…♥♥」",
  "target": "「哈ーっ♥ 哈ーっ♥ 为了不让精液漏出来被%ANAL_CALL()%堵住了…♥♥」"
 },
 {
  "source": "「ん啊啊っ♥♥ %ANAL_CALL()%…っ♥♥ オモチャで虐められてっ♥♥ お、おぉ…っ♥♥」",
  "target": "「嗯啊啊っ♥♥ %ANAL_CALL()%…っ♥♥ 被玩具欺负着♥♥ 哦、哦…っ♥♥」"
 },
 {
  "source": "「んぎぃっ♥……い、勢いよく引き抜くなぁ…っ♥♥」",
  "target": "「嗯咿っ♥……别、别那么猛力拔出来啊…っ♥♥」"
 },
 {
  "source": "「はあ♥ 噗啊♥ …ぽ、ぽっかり広がって戻らなくなった%ANAL_CALL()%♥♥\\n　最低に下品で恥ずかしい地方、%MASTER_CALL()%に晒してるぅ♥♥」",
  "target": "「哈啊♥ 噗啊♥ …空、空荡荡地合不拢的%ANAL_CALL()%♥♥\\n　把最下流最羞耻的地方暴露给%MASTER_CALL()%了♥♥」"
 },
 {
  "source": "「んお゛おぉっ♥♥ %ANAL_CALL()%弱いからぁ♥♥ ゆるひてくれぇ♥♥」",
  "target": "「嗯哦哦っ♥♥ %ANAL_CALL()%太弱了♥♥ 饶了我吧♥♥」"
 },
 {
  "source": "「ほ咿♥ ほ咿♥ 感じすぎて腰ヘコ止まんね…っ♥♥」",
  "target": "「嚯咿♥ 嚯咿♥ 感觉太强腰停不下来了…っ♥♥」"
 },
 {
  "source": "「啊咿ぃ♥♥ こんなオモチャでぇ…♥♥ ブザマに高潮きめちま呜呜♥♥♥」",
  "target": "「啊咿♥♥ 被这种玩具…♥♥ 难堪地高潮了呜呜♥♥♥」"
 },
 {
  "source": "「啊—♥ 啊—♥ 偽物の%PENIS_CALL()%でも%ANAL_CALL()%感じちまってるぅっ♥♥」",
  "target": "「啊—♥ 啊—♥ 就算是假货的%PENIS_CALL()%%ANAL_CALL()%也有感觉了♥♥」"
 },
 {
  "source": "「哈咿♥ %ANAL_CALL()%っ♥♥ オモチャで遊ばれてるぅっ♥♥」",
  "target": "「哈咿♥ %ANAL_CALL()%っ♥♥ 被玩具玩弄着♥♥」"
 },
 {
  "source": "「哦♥ 哦♥ アナル按摩棒で無様にヨガる变态奴隶に調教されてしまいましたぁ♥♥」",
  "target": "「哦♥ 哦♥ 被肛门按摩棒调教成了难堪地扭动的变态奴隶了♥♥」"
 },
 {
  "source": "「ひぅっ♥♥ し、振動つよ…っ ほぉぉっ♥♥」",
  "target": "「咻っ♥♥ 振、振动好强…っ 嚯哦哦っ♥♥」"
 },
 {
  "source": "「ん啊啊っ♥♥ ２穴責めっ♥♥ 耐えらんないぃっ♥♥♥」",
  "target": "「嗯啊啊っ♥♥ ２穴責めっ♥♥ 受不了了ぃっ♥♥♥」"
 },
 {
  "source": "「ほーっ♥♥ ほーっ♥♥ 処女のまま%ANAL_CALL()%開発されるなんてぇ…♥♥」",
  "target": "「呼ーっ♥♥ 呼ーっ♥♥ 処女のまま就被开发%ANAL_CALL()%なんてぇ…♥♥」"
 },
 {
  "source": "「ぬ、抜いてくれぇっ♥ %ANAL_CALL()%がおかしくなりそうだってぇっ♥♥」",
  "target": "「给、给我拔出来ぇっ♥ %ANAL_CALL()%要变得不对劲了ってぇっ♥♥」"
 },
 {
  "source": "「ぅ啊啊…♥ こんなので、感じたくねえのに…♥」",
  "target": "「呜啊啊…♥ 明明不想被这种东西搞出感觉的…♥」"
 },
 {
  "source": "「いぎぃっ♥ た、頼むからっ…！ 抜いてくれっ！」",
  "target": "「要去了ぃっ♥ 拜、拜托了っ…！ 给我拔出来っ！」"
 },
 {
  "source": "「は、腹ン中で動いてっ…くるしいっ…う咕呜…♥」",
  "target": "「在、在肚子里动着っ…好难受っ…呜咕呜…♥」"
 },
 {
  "source": "「喂，♥ 乳头の芯まで震えが伝わって…♥ あ、啊啊…♥」",
  "target": "「喂，♥ 震感都传到乳头深处了…♥ 啊、啊啊…♥」"
 },
 {
  "source": "「んいぃっ♥♥ %MASTER_CALL()%に直接触れられたいのにぃっ♥ オモチャで気持ちよくなってるぅ♥♥」",
  "target": "「唔いぃっ♥♥ 明明想被%MASTER_CALL()%直接碰的ぃっ♥ 却被玩具搞得这么舒服ぅ♥♥」"
 },
 {
  "source": "「はへっ♥ はへっ♥ 奶头責めっ♥ 应该かしくて好舒服っ♥♥」",
  "target": "「哈嘿っ♥ 哈嘿っ♥ 奶头責めっ♥ 又痒又舒服っ♥♥」"
 },
 {
  "source": "「んぅ…っ♥ 刺激がつよ…いっ♥……っ♥」",
  "target": "「唔…っ♥ 刺激太强…了っ♥……っ♥」"
 },
 {
  "source": "「啊♥ 啊♥ やめ…胸をいじるなぁ…♥」",
  "target": "「啊♥ 啊♥ 住手…别碰我胸ぁ…♥」"
 },
 {
  "source": "「はぅぅ♥♥ お豆がぁ♥ %PENIS_CALL()%みたいに勃起してるぅ♥♥」",
  "target": "「哈呜呜♥♥ 小豆豆ぁ♥ 像%PENIS_CALL()%一样勃起了ぅ♥♥」"
 },
 {
  "source": "「啊咿っ♥ 振動責めがっ♥ いつまでも終らないっ♥♥♥」",
  "target": "「啊咿っ♥ 振動責めっ♥ 怎么都停不下来っ♥♥♥」"
 },
 {
  "source": "「んおぉ…♥♥ オモチャなんかにいいように弄ばれて…っ♥ ほおおぉぉっ♥♥」",
  "target": "「唔哦ぉ…♥♥ 被玩具这种东西随便玩弄…っ♥ 嚯哦おぉぉっ♥♥」"
 },
 {
  "source": "「あ咿♥ あ咿♥ 刺激が強すぎるぅっ…♥♥」",
  "target": "「啊咿♥ 啊咿♥ 刺激太强了ぅっ…♥♥」"
 },
 {
  "source": "「そ、そこぉっ♥ 敏感な所所以ぁ…ん啊♥」",
  "target": "「那、那里ぉっ♥ 敏感的地方ぁ…嗯啊♥」"
 },
 {
  "source": "「ひ呜呜♥ 外してくれぇっ…頼むからぁ…っ♥」",
  "target": "「咿呜呜♥ 快拿掉ぇっ…求你了ぁ…っ♥」"
 },
 {
  "source": "「あぅぅっ♥ 感じすぎて…く、苦しい…♥」",
  "target": "「啊呜呜っ♥ 感觉太强了…好、好难受…♥」"
 },
 {
  "source": "「咿咕♥……はー♥…はー♥…奶头引っ張られるぅ♥」",
  "target": "「咿咕♥……哈ー♥…哈ー♥…奶头被拉扯ぅ♥」"
 },
 {
  "source": "「咿咕♥……はーっ♥…はーっ♥…お豆が引っ張られるぅ♥」",
  "target": "「咿咕♥……哈ーっ♥…哈ーっ♥…小豆豆被拉扯ぅ♥」"
 },
 {
  "source": "「んぅぅ♥…っ……いっ♥……ん嗯…♥♥」",
  "target": "「唔呜呜♥…っ……嗯っ♥……嗯嗯…♥♥」"
 },
 {
  "source": "「んぅぅ…っ……いっ……呜呜…」",
  "target": "「唔呜呜…っ……嗯っ……呜呜…」"
 },
 {
  "source": "「ん啊啊ぁっ！？ み、耳から入ってき―― あ゛っ♥ 啊♥ ぁっ♥ ぁ……」",
  "target": "「嗯啊啊ぁっ！？ 从、耳朵里进来了―― 啊゛っ♥ 啊♥ 啊っ♥ 啊……」"
 },
 {
  "source": "「%MASTER_CALL()%♥ 性処理ペットの%CALLNAME%に何でも命令してくれよ♥♥」",
  "target": "「%MASTER_CALL()%♥ 尽管命令你的性处理宠物%CALLNAME%做任何事吧♥♥」"
 },
 {
  "source": "「ん………嗯嗯…？ %SELF_CALL()%、一体どうなって……？」",
  "target": "「嗯………嗯嗯…？ %SELF_CALL()%、到底怎么回事……？」"
 },
 {
  "source": "「んお゛おぉぉっ♥♥ 身体の一番奥ぅっ♥♥ 快感で灼けつ咕呜♥♥」",
  "target": "「唔哦゛哦ぉぉっ♥♥ 身体最深处ぅっ♥♥ 快感烧灼着咕呜♥♥」"
 },
 {
  "source": "「哈咿ぃっ♥♥♥ その魔術は……ゆ、許し――ふぎぃぃぃっ♥♥♥」",
  "target": "「哈咿ぃっ♥♥♥ 那魔术……不、不可饶恕――唔ぎぃぃぃっ♥♥♥」"
 },
 {
  "source": "「啊ー♥ 啊♥ 啊♥ …腹が熱い…っ♥ これ…まさか…っ♥」",
  "target": "「啊ー♥ 啊♥ 啊♥ …肚子好热…っ♥ 这…难道…っ♥」"
 },
 {
  "source": "「……ふ、呼呼♥…呼呼呼呼♥♥ 奴隶に刻む所有者のシルシ…♥♥\\n　一生%MASTER_CALL()%のモノだって证明を貰っちまった…♥♥」",
  "target": "「……呵、呼呼♥…呼呼呼呼♥♥ 刻在奴隶身上的所有者的印记…♥♥\\n　这下算是收到了这辈子都是%MASTER_CALL()%的东西的证明了…♥♥」"
 },
 {
  "source": "「哈啊♥…哈啊♥……これで一生、家畜にしてもらえるってことだよな…♥♥♥」",
  "target": "「哈啊♥…哈啊♥……也就是说，这辈子能给你当牲口了是吧…♥♥♥」"
 },
 {
  "source": "「哈啊♥…哈啊♥……ふ、呼呼♥♥ 已经絶対に逃げられなくなっちまった…♥♥」",
  "target": "「哈啊♥…哈啊♥……呵、呼呼♥♥ 已经绝对逃不掉了…♥♥」"
 },
 {
  "source": "「ほ、ほぎいいぃぃぃ～～～っ♥♥ 哦♥ 呜呜呜♥ ふお゛おおぉぉぉ～～～っ♥♥♥」",
  "target": "「嚯、嚯咿いいぃぃぃ～～～っ♥♥ 哦♥ 呜呜呜♥ 唔哦゛哦哦ぉぉぉ～～～っ♥♥♥」"
 },
 {
  "source": "「咿ぐ呜呜ぅぅ～～っ♥♥♥ あ゛っ♥ あ゛っ♥ 啊ー♥ …んい゛いぃぃぃぃっ♥♥♥♥」",
  "target": "「咿咕呜呜ぅぅ～～っ♥♥♥ 啊゛っ♥ 啊゛っ♥ 啊ー♥ …嗯い゛いぃぃぃぃっ♥♥♥♥」"
 },
 {
  "source": "「啊呜♥…お゛ぉっ♥……こ、これで…えいえんに……%MASTER_CALL()%…♥♥」",
  "target": "「啊呜♥…哦゛ぉっ♥……这、这下…永远……都是%MASTER_CALL()%的了…♥♥」"
 },
 {
  "source": "「か咿♥ 哈咿♥ ……ほ、真的の……めすうし…に……♥♥」",
  "target": "「咔咿♥ 哈咿♥ ……真、真的……成母牛…了……♥♥」"
 },
 {
  "source": "「は咿♥…へ咿♥……もどし…こ、こんなからだ……やぁ…♥♥」",
  "target": "「哈咿♥…嘿咿♥……还给我…这、这副身体……不要ぁ…♥♥」"
 },
 {
  "source": "「嗯嗯…♥♥ %ANAL_CALL()%をいっぱい可愛がってほしい…♥♥」",
  "target": "「嗯嗯…♥♥ 想让%ANAL_CALL()%被好好疼爱…♥♥」"
 },
 {
  "source": "「ん嗯♥♥ ヒクヒクしてるのは別に期待とかじゃ……\\n　……啊啊已经っ！ 期待して悪いかよぉっ♥♥」",
  "target": "「嗯嗯♥♥ 在那儿抽动可不是因为期待什么……\\n　……啊啊已经っ！ 期待了又怎样啊ぉっ♥♥」"
 },
 {
  "source": "「哈啊♥ 噗啊♥ %SWEET_MASTER_CALL()%♥♥…%ANAL_CALL()%でイかせまくってくれよなぁ♥♥」",
  "target": "「哈啊♥ 噗啊♥ %SWEET_MASTER_CALL()%♥♥…用%ANAL_CALL()%让我高潮到死吧ぁ♥♥」"
 },
 {
  "source": "「呜呜ぅ…%ANAL_CALL()%弱いの認めるから……イかせまくるのは勘弁してくれ…」",
  "target": "「呜呜ぅ…我承认%ANAL_CALL()%比较弱……所以饶了我别让我一直高潮了…」"
 },
 {
  "source": "「啊啊……ヤバい…%ANAL_CALL()%弱点なのに…」",
  "target": "「啊啊……不妙…明明%ANAL_CALL()%是我的弱点的…」"
 },
 {
  "source": "「ま、まて…%ANAL_CALL()%に何するつもりだ…っ」",
  "target": "「等、等等…你打算对%ANAL_CALL()%干什么…っ」"
 },
 {
  "source": "「ひゃ嗯…つめてっ……」",
  "target": "「咿呀嗯…好凉っ……」"
 },
 {
  "source": "「はあ♥ はあ♥ 更加気持ちよくなれる薬だったよな…♥♥」",
  "target": "「哈啊♥ 哈啊♥ 是能让人更爽的药对吧…♥♥」"
 },
 {
  "source": "「これでより深く%MASTER_CALL()%を感じられるんだな…♥♥」",
  "target": "「这样就能更深地感受到%MASTER_CALL()%了…♥♥」"
 },
 {
  "source": "「うっ…何だよこの薬……っ」",
  "target": "「唔…这药怎么回事啊……っ」"
 },
 {
  "source": "「哈咿♥…哈咿♥…%SWEET_MASTER_CALL()%♥♥ 我慢できねえんだよぉ…早くぅ♥♥」",
  "target": "「哈咿♥…哈咿♥…%SWEET_MASTER_CALL()%♥♥ 忍不住了啊ぉ…快点ぅ♥♥」"
 },
 {
  "source": "「哈啊♥…哈啊♥……ヤリたすぎて…抵抗できない…♥」",
  "target": "「哈啊♥…哈啊♥……太想干了…根本抵抗不了…♥」"
 },
 {
  "source": "「はー♥♥ %MASTER_CALL()%が見えると安心するな♥♥」",
  "target": "「哈ー♥♥ 看到%MASTER_CALL()%就安心了な♥♥」"
 },
 {
  "source": "「口枷をすると%MASTER_CALL()%に好きって言えなくなるのが欠点だな♥」",
  "target": "「戴上口枷就没法对%MASTER_CALL()%说喜欢了，这点不太好な♥」"
 },
 {
  "source": "「%SWEET_MASTER_CALL()%♥ 量が多すぎて、どんどんあふれてくるぅ…♥♥」",
  "target": "「%SWEET_MASTER_CALL()%♥ 量太多了，不停往外溢ぅ…♥♥」"
 },
 {
  "source": "「啊啊…♥ 膣内射精ザーメンでどろどろの%VAGINA_CALL()%♥…すげえ好色…♥♥」",
  "target": "「啊啊…♥ 被膣内射精精液搞得黏糊糊的%VAGINA_CALL()%♥…真他妈色…♥♥」"
 },
 {
  "source": "「……啊—…%ANAL_CALL()%が%PENIS_CALL()%の形に広がって戻らない…♥」",
  "target": "「……啊—…%ANAL_CALL()%被撑成%PENIS_CALL()%的形状回不去了…♥」"
 },
 {
  "source": "「んお゛ぉっ♥♥…お゛ぉ♥……勢いよく引き抜かれ…て…っ♥♥」",
  "target": "「唔哦゛ぉっ♥♥…哦゛ぉ♥……被猛地拔了出…来…っ♥♥」"
 },
 {
  "source": "「%SWEET_MASTER_CALL()%♥ 量が多すぎて、どんどんあふれてくるぅ♥♥」",
  "target": "「%SWEET_MASTER_CALL()%♥ 量多到一直往外溢啊♥♥」"
 },
 {
  "source": "「あ、あぅぅ…♥ %ANAL_CALL()%から精液ブリュブリュ排泄する音、聞かないでくれぇ…♥」",
  "target": "「啊、啊唔唔…♥ 别听%ANAL_CALL()%噗噜噗噜往外排精液的声音啊…♥」"
 },
 {
  "source": "「啊啊♥♥ %PENIS_CALL()%抜かれたら%ANAL_CALL()%が寂しいんだよぉ…♥♥」",
  "target": "「啊啊♥♥ %PENIS_CALL()%一拔出去%ANAL_CALL()%就好寂寞啊…♥♥」"
 },
 {
  "source": "「んおぉっ♥♥ %PENIS_CALL()%抜いたらやらぁ…♥♥」",
  "target": "「嗯哦っ♥♥ 敢拔%PENIS_CALL()%有你好看…♥♥」"
 },
 {
  "source": "「呼呼♥♥ 胸と%PENIS_CALL()%がザーメンの糸で繋がってるじゃ嗯♥♥」",
  "target": "「呼呼♥♥ 胸和%PENIS_CALL()%被精液的丝连在一起了嘛嗯♥♥」"
 },
 {
  "source": "「おぉ…♥ 谷間に精液の橋が…♥♥ なんて濃厚さだよ…♥♥」",
  "target": "「哦…♥ 乳沟上有精液的桥…♥♥ 真够浓的啊…♥♥」"
 },
 {
  "source": "「嘻嘻 奶子乳汁とザーメン乳汁でどろどろになっちまったな…♥♥」",
  "target": "「嘻嘻 奶水和精液搞得黏糊糊的了啊…♥♥」"
 },
 {
  "source": "「精液と母乳の特製ローション♥ むせかえるような薫りでクラクラすんぜ…♥♥」",
  "target": "「精液和母乳特制润滑液♥ 呛人的味道熏得我头晕啊…♥♥」"
 },
 {
  "source": "「けふっ♥ ごちそうさま、%MASTER_CALL()%♥♥」",
  "target": "「咳呼っ♥ 多谢款待、%MASTER_CALL()%♥♥」"
 },
 {
  "source": "「おぉ♥ %MASTER_CALL()%♥ 谢谢な♥♥」",
  "target": "「哦♥ %MASTER_CALL()%♥ 谢了啊♥♥」"
 },
 {
  "source": "「嘻嘻 優しいんだな、%MASTER_CALL()%♥♥」",
  "target": "「嘻嘻 你还挺温柔的嘛、%MASTER_CALL()%♥♥」"
 },
 {
  "source": "「%SWEET_MASTER_CALL()%♥♥…客气なく突きこんでくれよなぁ♥♥」",
  "target": "「%SWEET_MASTER_CALL()%♥♥…别客气直接干进来啊♥♥」"
 },
 {
  "source": "「啊啊…♥ %MASTER_CALL()%的%PENIS_CALL()%が入ってくる…♥♥」",
  "target": "「啊啊…♥ %MASTER_CALL()%的%PENIS_CALL()%进来了…♥♥」"
 },
 {
  "source": "「哈嗯♥ %VAGINA_CALL()%の奥まで広げられてる…♥♥」",
  "target": "「哈嗯♥ 连%VAGINA_CALL()%深处都被撑开了…♥♥」"
 },
 {
  "source": "「……抵抗しないから…苦しいこととか痛いこととかはやめろよな…」",
  "target": "「……我又不反抗…所以别弄那些又难受又疼的事啊…」"
 },
 {
  "source": "「こんなの……不要啊…」",
  "target": "「这种的……不要啊…」"
 },
 {
  "source": "「咕呜ぅ…屈辱だっての…」",
  "target": "「咕呜…这也太屈辱了吧…」"
 },
 {
  "source": "「哦♥ 哦♥ そんなに突かれたら、すぐ去ちまうっ♥♥ ん嗯♥♥」",
  "target": "「哦♥ 哦♥ 被那么顶的话、马上去了啊っ♥♥ 嗯嗯♥♥」"
 },
 {
  "source": "「喂，♥ %PENIS_CALL()%呃♥ いい所ばかり当たって…っ♥♥ 啊♥ 啊♥ 啊♥」",
  "target": "「喂、♥ %PENIS_CALL()%呃♥ 净顶在好地方啊…っ♥♥ 啊♥ 啊♥ 啊♥」"
 },
 {
  "source": "「あ咿♥ あ咿♥ 子宮口が%PENIS_CALL()%にコツンコツンってノックされてるぅ♥♥」",
  "target": "「啊咿♥ 啊咿♥ 子宫口被%PENIS_CALL()%咚咚地敲门呢♥♥」"
 },
 {
  "source": "「んぁっ♥ 啊啊っ♥ お互いの肉がぶつかって、情熱的だな…♥♥♥」",
  "target": "「嗯啊っ♥ 啊啊っ♥ 彼此的肉撞在一起、真够热情的啊…♥♥♥」"
 },
 {
  "source": "「啊♥ 啊♥ %SWEET_MASTER_CALL()%♥ 更加乱暴に……力づくで犯してほしい…っ♥♥♥」",
  "target": "「啊♥ 啊♥ %SWEET_MASTER_CALL()%♥ 再粗暴点……用蛮力干我…っ♥♥♥」"
 },
 {
  "source": "「ん哦♥ おぉっ♥ 身動きとれずに犯されるの、非常興奮する♥♥ んおぉっ♥♥」",
  "target": "「嗯哦♥ 哦っ♥ 动弹不得地被干、超兴奋的♥♥ 嗯哦っ♥♥」"
 },
 {
  "source": "「嗯♥♥ 別に相性なんて良くねーし……ん嗯♥」",
  "target": "「嗯♥♥ 谁跟你合得来了……嗯嗯♥」"
 },
 {
  "source": "「ふっ♥…ん嗯♥……その動き、不行だって…♥」",
  "target": "「呼っ♥…嗯嗯♥……那个动作、不行啊…♥」"
 },
 {
  "source": "「うぐっ♥…やめ……許してくれ…っ」",
  "target": "「呃咕っ♥…住手……饶了我…っ」"
 },
 {
  "source": "「哦♥…おぉ…♥ %ANAL_CALL()%がこじ開けられてる…♥♥」",
  "target": "「哦♥…哦…♥ %ANAL_CALL()%被撬开了…♥♥」"
 },
 {
  "source": "「は啊啊ぁ♥♥ %ANAL_CALL()%着%PENIS_CALL()%きたぁ♥♥♥」",
  "target": "「哈啊啊啊♥♥ %ANAL_CALL()%被%PENIS_CALL()%插进来了啊♥♥♥」"
 },
 {
  "source": "「ふっ…ん嗯♥ %SELF_CALL()%的%ANAL_CALL()%、たっぷり躾けてほしい♥♥」",
  "target": "「呼…嗯嗯♥ 我的%ANAL_CALL()%、好好调教一下吧♥♥」"
 },
 {
  "source": "「%SWEET_MASTER_CALL()%♥ %ANAL_CALL()%がガバガバになるまで突いてくれよ♥♥」",
  "target": "「%SWEET_MASTER_CALL()%♥ 把%ANAL_CALL()%干到松松垮垮的吧♥♥」"
 },
 {
  "source": "「んほぉっ！？♥♥……お…おぉ…♥♥ ズ、ズルって入り込んで…っ♥♥」",
  "target": "「嗯嚯っ！？♥♥……哦…哦…♥♥ 哧、哧溜一下插进去了…っ♥♥」"
 },
 {
  "source": "「啊♥ 啊啊…♥ こんな…变态かよぉ…♥」",
  "target": "「啊♥ 啊啊…♥ 这…我是变态吗…♥」"
 },
 {
  "source": "「喂，♥ ん哦♥ ……き、期待なんかしてない…っ」",
  "target": "「喂、♥ 嗯哦♥ ……才、才没有期待呢…っ」"
 },
 {
  "source": "「はぅ…や、やめ……ん嗯♥」",
  "target": "「哈呜…别、别……嗯嗯♥」"
 },
 {
  "source": "「咿咕…！ い、痛い……やめろって……っ」",
  "target": "「咿咕…！ 好、好疼……让你住手啊……っ」"
 },
 {
  "source": "「ふおぉ♥♥ %PENIS_CALL()%で%ANAL_CALL()%をほじられて有感觉ぅっ♥♥」",
  "target": "「呼哦♥♥ %ANAL_CALL()%被%PENIS_CALL()%捅得有感觉了っ♥♥」"
 },
 {
  "source": "「嗯♥♥ 小刻みに動かすの…好舒服……んぁぁっ♥」",
  "target": "「嗯♥♥ 小幅地动…好舒服……嗯啊啊っ♥」"
 },
 {
  "source": "「は呜呜♥ %ANAL_CALL()%の奥まで更加念入りに突いてぇ♥♥」",
  "target": "「哈呜呜♥ 连%ANAL_CALL()%深处都更仔细地顶啊♥♥」"
 },
 {
  "source": "「ほ咿♥♥ %SWEET_MASTER_CALL()%♥♥ は、激しいぃ♥♥」",
  "target": "「嚯咿♥♥ %SWEET_MASTER_CALL()%♥♥ 好、好激烈啊啊♥♥」"
 },
 {
  "source": "「んほぉっ♥♥ %ANAL_CALL()%雑魚すぎてぇ♥♥ 高潮我慢できないぃ♥♥」",
  "target": "「嗯嚯っ♥♥ %ANAL_CALL()%太不争气了♥♥ 根本忍不住高潮啊♥♥」"
 },
 {
  "source": "「啊♥ あ嗯♥ %ANAL_CALL()%着%PENIS_CALL()%ねじ込まれたらぁ♥♥\\n　一発でメスの本性さらけ出ちゃ呜呜♥♥ 啊啊嗯♥♥」",
  "target": "「啊♥ 嗯嗯♥ %ANAL_CALL()%被%PENIS_CALL()%强行塞进来的话♥♥\\n　一下就得暴露母狗的本性了呜呜♥♥ 啊啊嗯♥♥」"
 },
 {
  "source": "「哈咿ぃ…♥♥ %SELF_CALL()%哈啊…未経験の処女のくせに%ANAL_CALL()%でヨガる变态れすぅ…♥♥」",
  "target": "「哈咿…♥♥ 我哈啊…明明是个没经验的处女却用%ANAL_CALL()%高潮的变态就是我…♥♥」"
 },
 {
  "source": "「ん哈啊♥♥ %VAGINA_CALL()%は未使用なのにぃ…♥♥ %ANAL_CALL()%はがっつり調教されちまったぁ♥♥」",
  "target": "「嗯哈啊♥♥ %VAGINA_CALL()%明明还没用过…♥♥ %ANAL_CALL()%却被彻底调教完了啊♥♥」"
 },
 {
  "source": "「んぉぉ♥♥ 前は処女のまま、後ろ只是ガバガバに開発するとかぁ…♥♥」",
  "target": "「嗯哦哦♥♥ 前面还是处女、后面却被开发得松松垮垮什么的…♥♥」"
 },
 {
  "source": "「哦♥ 哦♥ 哦♥ %ANAL_CALL()%がぁ♥ %VAGINA_CALL()%みたいに有感觉るぅ♥♥」",
  "target": "「哦♥ 哦♥ 哦♥ %ANAL_CALL()%啊♥ 变得跟%VAGINA_CALL()%一样有感觉了♥♥」"
 },
 {
  "source": "「嗯…嗯嗯…♥♥ ロリっ娘のキツキツの%ANAL_CALL()%♥ 客气なく突き込んでいいからな♥♥」",
  "target": "「嗯…嗯嗯…♥♥ 萝莉紧得要命的%ANAL_CALL()%♥ 不用客气直接插进来就行啊♥♥」"
 },
 {
  "source": "「啊♥ あぅっ♥ ちっちゃい%ANAL_CALL()%がケダモノの%PENIS_CALL()%に広げられてるぅっ♥♥」",
  "target": "「啊♥ 啊呜っ♥ 小小的%ANAL_CALL()%被禽兽一样的%PENIS_CALL()%撑开了啊っ♥♥」"
 },
 {
  "source": "「きゃ呜呜嗯♥♥ %MASTER_CALL()%の自分本位な身勝手ピストンきたぁ♥♥\\n　こんなに%SELF_CALL()%を求めてくれて、とにかく嬉しい…っ♥♥♥」",
  "target": "「呀呜呜嗯♥♥ %MASTER_CALL()%只顾自己爽的任性活塞来啦♥♥\\n　这么渴求我的身体、总之就是开心…っ♥♥♥」"
 },
 {
  "source": "「はっ♥ は咿♥ や、やめ…っ♥」",
  "target": "「哈っ♥ 哈咿♥ 住、住手…っ♥」"
 },
 {
  "source": "「啊♥ 啊♥ 小刻みに動かすのは……んぁっ♥」",
  "target": "「啊♥ 啊♥ 小幅地动的话……嗯啊っ♥」"
 },
 {
  "source": "「嗯♥…嗯♥……く、苦しくて声が出てる只是だっての…っ♥」",
  "target": "「嗯♥…嗯♥……我只是因为难受才出声的好吧…っ♥」"
 },
 {
  "source": "「はっ…はっ…か、有感觉訳ないだろ……嗯…♥」",
  "target": "「哈…哈…哪、哪可能有感觉啊……嗯…♥」"
 },
 {
  "source": "「ふぐっ……ひろがってる……っ」",
  "target": "「唔咕……被撑开了……っ」"
 },
 {
  "source": "「ん呜呜…♥♥ %ANAL_CALL()%にザーメン塗り込まれてるぅ…♥♥」",
  "target": "「嗯呜呜…♥♥ %ANAL_CALL()%上被涂满了精液啊…♥♥」"
 }
]